{"positionsByLap":[{"lap":1,"positions":{"VER":1,"GAS":17,"PER":7,"ALO":11,"LEC":4,"STR":8,"MAG":13,"TSU":9,"ALB":14,"ZHO":19,"HUL":16,"RIC":18,"OCO":15,"NOR":3,"HAM":10,"SAI":2,"RUS":6,"BOT":12,"PIA":5}},{"lap":2,"positions":{"VER":2,"GAS":17,"PER":7,"ALO":11,"LEC":4,"STR":8,"MAG":13,"TSU":9,"ALB":14,"ZHO":19,"HUL":16,"RIC":18,"OCO":15,"NOR":3,"HAM":10,"SAI":1,"RUS":6,"BOT":12,"PIA":5}},{"lap":3,"positions":{"VER":2,"GAS":17,"PER":7,"ALO":11,"LEC":4,"STR":8,"MAG":13,"TSU":9,"ALB":14,"ZHO":19,"HUL":16,"RIC":18,"OCO":15,"NOR":3,"HAM":10,"SAI":1,"RUS":6,"BOT":12,"PIA":5}},{"lap":4,"positions":{"VER":19,"GAS":16,"PER":6,"ALO":10,"LEC":3,"STR":7,"MAG":12,"TSU":8,"ALB":13,"ZHO":18,"HUL":15,"RIC":17,"OCO":14,"NOR":2,"HAM":9,"SAI":1,"RUS":5,"BOT":11,"PIA":4}},{"lap":5,"positions":{"VER":19,"GAS":16,"PER":6,"ALO":10,"LEC":3,"STR":7,"MAG":12,"TSU":8,"ALB":13,"ZHO":17,"HUL":15,"RIC":18,"OCO":14,"NOR":2,"HAM":9,"SAI":1,"RUS":5,"BOT":11,"PIA":4}},{"lap":6,"positions":{"VER":19,"GAS":15,"PER":6,"ALO":10,"LEC":3,"STR":7,"MAG":12,"TSU":8,"ALB":16,"ZHO":17,"HUL":14,"RIC":18,"OCO":13,"NOR":2,"HAM":9,"SAI":1,"RUS":5,"BOT":11,"PIA":4}},{"lap":7,"positions":{"VER":19,"GAS":13,"PER":6,"ALO":9,"LEC":3,"STR":7,"MAG":15,"TSU":8,"ALB":16,"ZHO":18,"HUL":12,"RIC":17,"OCO":11,"NOR":2,"HAM":14,"SAI":1,"RUS":5,"BOT":10,"PIA":4}},{"lap":8,"positions":{"VER":19,"GAS":10,"PER":5,"ALO":7,"LEC":3,"STR":12,"MAG":15,"TSU":6,"ALB":14,"ZHO":17,"HUL":9,"RIC":16,"OCO":8,"NOR":2,"HAM":13,"SAI":1,"RUS":11,"BOT":18,"PIA":4}},{"lap":9,"positions":{"VER":19,"GAS":8,"PER":3,"ALO":4,"LEC":5,"STR":11,"MAG":15,"TSU":9,"ALB":14,"ZHO":17,"HUL":7,"RIC":16,"OCO":13,"NOR":2,"HAM":12,"SAI":1,"RUS":10,"BOT":18,"PIA":6}},{"lap":10,"positions":{"VER":19,"GAS":6,"PER":3,"ALO":4,"LEC":7,"STR":10,"MAG":15,"TSU":12,"ALB":13,"ZHO":17,"HUL":5,"RIC":16,"OCO":14,"NOR":2,"HAM":11,"SAI":1,"RUS":9,"BOT":18,"PIA":8}},{"lap":11,"positions":{"VER":19,"GAS":8,"PER":3,"ALO":4,"LEC":5,"STR":10,"MAG":15,"TSU":12,"ALB":13,"ZHO":17,"HUL":6,"RIC":16,"OCO":14,"NOR":2,"HAM":11,"SAI":1,"RUS":9,"BOT":18,"PIA":7}},{"lap":12,"positions":{"VER":19,"GAS":8,"PER":3,"ALO":4,"LEC":5,"STR":10,"MAG":15,"TSU":12,"ALB":13,"ZHO":17,"HUL":7,"RIC":16,"OCO":14,"NOR":2,"HAM":11,"SAI":1,"RUS":9,"BOT":18,"PIA":6}},{"lap":13,"positions":{"VER":19,"GAS":8,"PER":3,"ALO":4,"LEC":5,"STR":10,"MAG":15,"TSU":12,"ALB":13,"ZHO":17,"HUL":7,"RIC":16,"OCO":14,"NOR":2,"HAM":11,"SAI":1,"RUS":9,"BOT":18,"PIA":6}},{"lap":14,"positions":{"VER":19,"GAS":8,"PER":6,"ALO":2,"LEC":4,"STR":10,"MAG":15,"TSU":12,"ALB":13,"ZHO":17,"HUL":7,"RIC":16,"OCO":14,"NOR":3,"HAM":11,"SAI":1,"RUS":9,"BOT":18,"PIA":5}},{"lap":15,"positions":{"VER":19,"GAS":7,"PER":10,"ALO":2,"LEC":3,"STR":9,"MAG":15,"TSU":12,"ALB":13,"ZHO":17,"HUL":6,"RIC":16,"OCO":14,"NOR":5,"HAM":11,"SAI":1,"RUS":8,"BOT":18,"PIA":4}},{"lap":16,"positions":{"VER":19,"GAS":8,"PER":10,"ALO":2,"LEC":3,"STR":9,"MAG":13,"TSU":11,"ALB":12,"ZHO":15,"HUL":6,"RIC":14,"OCO":16,"NOR":5,"HAM":18,"SAI":1,"RUS":7,"BOT":17,"PIA":4}},{"lap":17,"positions":{"VER":19,"GAS":14,"PER":8,"ALO":5,"LEC":2,"STR":7,"MAG":12,"TSU":9,"ALB":10,"ZHO":15,"HUL":11,"RIC":13,"OCO":17,"NOR":4,"HAM":18,"SAI":1,"RUS":6,"BOT":16,"PIA":3}},{"lap":18,"positions":{"VER":19,"GAS":15,"PER":7,"ALO":5,"LEC":2,"STR":8,"MAG":11,"TSU":9,"ALB":10,"ZHO":14,"HUL":12,"RIC":13,"OCO":17,"NOR":4,"HAM":18,"SAI":1,"RUS":6,"BOT":16,"PIA":3}},{"lap":19,"positions":{"VER":19,"GAS":15,"PER":7,"ALO":5,"LEC":2,"STR":8,"MAG":11,"TSU":9,"ALB":10,"ZHO":14,"HUL":12,"RIC":13,"OCO":17,"NOR":4,"HAM":18,"SAI":1,"RUS":6,"BOT":16,"PIA":3}},{"lap":20,"positions":{"VER":19,"GAS":15,"PER":7,"ALO":5,"LEC":2,"STR":8,"MAG":11,"TSU":9,"ALB":10,"ZHO":14,"HUL":12,"RIC":13,"OCO":17,"NOR":4,"HAM":18,"SAI":1,"RUS":6,"BOT":16,"PIA":3}},{"lap":21,"positions":{"VER":19,"GAS":15,"PER":6,"ALO":5,"LEC":2,"STR":8,"MAG":11,"TSU":9,"ALB":10,"ZHO":14,"HUL":12,"RIC":13,"OCO":17,"NOR":4,"HAM":18,"SAI":1,"RUS":7,"BOT":16,"PIA":3}},{"lap":22,"positions":{"VER":19,"GAS":15,"PER":6,"ALO":5,"LEC":2,"STR":8,"MAG":11,"TSU":9,"ALB":10,"ZHO":14,"HUL":12,"RIC":13,"OCO":17,"NOR":4,"HAM":18,"SAI":1,"RUS":7,"BOT":16,"PIA":3}},{"lap":23,"positions":{"VER":19,"GAS":15,"PER":6,"ALO":5,"LEC":2,"STR":8,"MAG":12,"TSU":9,"ALB":10,"ZHO":14,"HUL":11,"RIC":13,"OCO":17,"NOR":4,"HAM":18,"SAI":1,"RUS":7,"BOT":16,"PIA":3}},{"lap":24,"positions":{"VER":19,"GAS":15,"PER":6,"ALO":5,"LEC":2,"STR":8,"MAG":12,"TSU":9,"ALB":10,"ZHO":14,"HUL":11,"RIC":13,"OCO":17,"NOR":4,"HAM":18,"SAI":1,"RUS":7,"BOT":16,"PIA":3}},{"lap":25,"positions":{"VER":19,"GAS":15,"PER":6,"ALO":5,"LEC":2,"STR":8,"MAG":12,"TSU":9,"ALB":10,"ZHO":14,"HUL":11,"RIC":13,"OCO":17,"NOR":4,"HAM":18,"SAI":1,"RUS":7,"BOT":16,"PIA":3}},{"lap":26,"positions":{"VER":19,"GAS":15,"PER":6,"ALO":5,"LEC":2,"STR":8,"MAG":12,"TSU":9,"ALB":10,"ZHO":14,"HUL":11,"RIC":13,"OCO":17,"NOR":4,"HAM":18,"SAI":1,"RUS":7,"BOT":16,"PIA":3}},{"lap":27,"positions":{"VER":19,"GAS":14,"PER":5,"ALO":6,"LEC":2,"STR":8,"MAG":11,"TSU":9,"ALB":15,"ZHO":13,"HUL":10,"RIC":12,"OCO":17,"NOR":4,"HAM":18,"SAI":1,"RUS":7,"BOT":16,"PIA":3}},{"lap":28,"positions":{"VER":19,"GAS":14,"PER":5,"ALO":6,"LEC":2,"STR":8,"MAG":11,"TSU":9,"ALB":15,"ZHO":13,"HUL":10,"RIC":12,"OCO":17,"NOR":4,"HAM":18,"SAI":1,"RUS":7,"BOT":16,"PIA":3}},{"lap":29,"positions":{"VER":19,"GAS":13,"PER":5,"ALO":6,"LEC":2,"STR":8,"MAG":11,"TSU":9,"ALB":14,"ZHO":12,"HUL":10,"RIC":15,"OCO":17,"NOR":3,"HAM":18,"SAI":1,"RUS":7,"BOT":16,"PIA":4}},{"lap":30,"positions":{"VER":19,"GAS":13,"PER":5,"ALO":6,"LEC":2,"STR":8,"MAG":11,"TSU":9,"ALB":14,"ZHO":12,"HUL":10,"RIC":17,"OCO":16,"NOR":3,"HAM":18,"SAI":1,"RUS":7,"BOT":15,"PIA":4}},{"lap":31,"positions":{"VER":19,"GAS":13,"PER":5,"ALO":6,"LEC":2,"STR":8,"MAG":11,"TSU":9,"ALB":14,"ZHO":12,"HUL":10,"RIC":17,"OCO":16,"NOR":3,"HAM":18,"SAI":1,"RUS":7,"BOT":15,"PIA":4}},{"lap":32,"positions":{"VER":19,"GAS":13,"PER":5,"ALO":6,"LEC":2,"STR":8,"MAG":11,"TSU":9,"ALB":14,"ZHO":12,"HUL":10,"RIC":17,"OCO":16,"NOR":3,"HAM":18,"SAI":1,"RUS":7,"BOT":15,"PIA":4}},{"lap":33,"positions":{"VER":19,"GAS":12,"PER":5,"ALO":6,"LEC":2,"STR":8,"MAG":13,"TSU":9,"ALB":14,"ZHO":11,"HUL":10,"RIC":17,"OCO":16,"NOR":3,"HAM":18,"SAI":1,"RUS":7,"BOT":15,"PIA":4}},{"lap":34,"positions":{"VER":19,"GAS":12,"PER":5,"ALO":6,"LEC":4,"STR":8,"MAG":14,"TSU":9,"ALB":13,"ZHO":11,"HUL":10,"RIC":17,"OCO":16,"NOR":2,"HAM":18,"SAI":1,"RUS":7,"BOT":15,"PIA":3}},{"lap":35,"positions":{"VER":19,"GAS":10,"PER":7,"ALO":5,"LEC":4,"STR":8,"MAG":13,"TSU":9,"ALB":12,"ZHO":17,"HUL":11,"RIC":16,"OCO":15,"NOR":2,"HAM":18,"SAI":1,"RUS":6,"BOT":14,"PIA":3}},{"lap":36,"positions":{"VER":19,"GAS":10,"PER":8,"ALO":5,"LEC":4,"STR":7,"MAG":13,"TSU":9,"ALB":12,"ZHO":17,"HUL":11,"RIC":15,"OCO":14,"NOR":2,"HAM":18,"SAI":1,"RUS":6,"BOT":16,"PIA":3}},{"lap":37,"positions":{"VER":19,"GAS":9,"PER":7,"ALO":5,"LEC":4,"STR":8,"MAG":13,"TSU":10,"ALB":12,"ZHO":17,"HUL":11,"RIC":15,"OCO":14,"NOR":2,"HAM":18,"SAI":1,"RUS":6,"BOT":16,"PIA":3}},{"lap":38,"positions":{"VER":19,"GAS":9,"PER":7,"ALO":5,"LEC":4,"STR":8,"MAG":13,"TSU":10,"ALB":12,"ZHO":17,"HUL":11,"RIC":14,"OCO":15,"NOR":2,"HAM":18,"SAI":1,"RUS":6,"BOT":16,"PIA":3}},{"lap":39,"positions":{"VER":19,"GAS":9,"PER":7,"ALO":5,"LEC":3,"STR":8,"MAG":13,"TSU":10,"ALB":12,"ZHO":17,"HUL":11,"RIC":14,"OCO":15,"NOR":2,"HAM":18,"SAI":1,"RUS":6,"BOT":16,"PIA":4}},{"lap":40,"positions":{"VER":19,"GAS":10,"PER":7,"ALO":4,"LEC":3,"STR":8,"MAG":13,"TSU":9,"ALB":12,"ZHO":17,"HUL":11,"RIC":14,"OCO":15,"NOR":2,"HAM":18,"SAI":1,"RUS":6,"BOT":16,"PIA":5}},{"lap":41,"positions":{"VER":19,"GAS":15,"PER":6,"ALO":7,"LEC":2,"STR":8,"MAG":12,"TSU":9,"ALB":11,"ZHO":17,"HUL":10,"RIC":13,"OCO":14,"NOR":3,"HAM":18,"SAI":1,"RUS":5,"BOT":16,"PIA":4}},{"lap":42,"positions":{"VER":19,"GAS":14,"PER":6,"ALO":7,"LEC":2,"STR":8,"MAG":12,"TSU":9,"ALB":11,"ZHO":17,"HUL":10,"RIC":13,"OCO":16,"NOR":3,"HAM":18,"SAI":1,"RUS":5,"BOT":15,"PIA":4}},{"lap":43,"positions":{"VER":19,"GAS":14,"PER":6,"ALO":7,"LEC":2,"STR":8,"MAG":12,"TSU":9,"ALB":11,"ZHO":16,"HUL":10,"RIC":13,"OCO":17,"NOR":3,"HAM":18,"SAI":1,"RUS":5,"BOT":15,"PIA":4}},{"lap":44,"positions":{"VER":19,"GAS":14,"PER":6,"ALO":7,"LEC":2,"STR":8,"MAG":11,"TSU":9,"ALB":12,"ZHO":16,"HUL":10,"RIC":13,"OCO":17,"NOR":3,"HAM":18,"SAI":1,"RUS":5,"BOT":15,"PIA":4}},{"lap":45,"positions":{"VER":19,"GAS":14,"PER":5,"ALO":7,"LEC":2,"STR":8,"MAG":11,"TSU":9,"ALB":12,"ZHO":16,"HUL":10,"RIC":13,"OCO":17,"NOR":3,"HAM":18,"SAI":1,"RUS":6,"BOT":15,"PIA":4}},{"lap":46,"positions":{"VER":19,"GAS":14,"PER":5,"ALO":6,"LEC":2,"STR":8,"MAG":11,"TSU":9,"ALB":12,"ZHO":16,"HUL":10,"RIC":13,"OCO":17,"NOR":3,"HAM":18,"SAI":1,"RUS":7,"BOT":15,"PIA":4}},{"lap":47,"positions":{"VER":19,"GAS":14,"PER":5,"ALO":6,"LEC":2,"STR":8,"MAG":11,"TSU":9,"ALB":12,"ZHO":16,"HUL":10,"RIC":13,"OCO":17,"NOR":3,"HAM":18,"SAI":1,"RUS":7,"BOT":15,"PIA":4}},{"lap":48,"positions":{"VER":19,"GAS":14,"PER":5,"ALO":6,"LEC":2,"STR":8,"MAG":11,"TSU":9,"ALB":12,"ZHO":16,"HUL":10,"RIC":13,"OCO":17,"NOR":3,"HAM":18,"SAI":1,"RUS":7,"BOT":15,"PIA":4}},{"lap":49,"positions":{"VER":19,"GAS":14,"PER":5,"ALO":6,"LEC":2,"STR":8,"MAG":11,"TSU":9,"ALB":12,"ZHO":16,"HUL":10,"RIC":13,"OCO":17,"NOR":3,"HAM":18,"SAI":1,"RUS":7,"BOT":15,"PIA":4}},{"lap":50,"positions":{"VER":19,"GAS":14,"PER":5,"ALO":6,"LEC":2,"STR":8,"MAG":11,"TSU":9,"ALB":12,"ZHO":16,"HUL":10,"RIC":13,"OCO":17,"NOR":3,"HAM":18,"SAI":1,"RUS":7,"BOT":15,"PIA":4}},{"lap":51,"positions":{"VER":19,"GAS":14,"PER":5,"ALO":6,"LEC":2,"STR":8,"MAG":11,"TSU":9,"ALB":12,"ZHO":16,"HUL":10,"RIC":13,"OCO":17,"NOR":3,"HAM":18,"SAI":1,"RUS":7,"BOT":15,"PIA":4}},{"lap":52,"positions":{"VER":19,"GAS":14,"PER":5,"ALO":6,"LEC":2,"STR":8,"MAG":11,"TSU":9,"ALB":12,"ZHO":16,"HUL":10,"RIC":13,"OCO":17,"NOR":3,"HAM":18,"SAI":1,"RUS":7,"BOT":15,"PIA":4}},{"lap":53,"positions":{"VER":19,"GAS":14,"PER":5,"ALO":6,"LEC":2,"STR":8,"MAG":11,"TSU":9,"ALB":12,"ZHO":16,"HUL":10,"RIC":13,"OCO":17,"NOR":3,"HAM":18,"SAI":1,"RUS":7,"BOT":15,"PIA":4}},{"lap":54,"positions":{"VER":19,"GAS":14,"PER":5,"ALO":6,"LEC":2,"STR":8,"MAG":11,"TSU":9,"ALB":12,"ZHO":16,"HUL":10,"RIC":13,"OCO":17,"NOR":3,"HAM":18,"SAI":1,"RUS":7,"BOT":15,"PIA":4}},{"lap":55,"positions":{"VER":19,"GAS":14,"PER":5,"ALO":6,"LEC":2,"STR":8,"MAG":11,"TSU":9,"ALB":12,"ZHO":16,"HUL":10,"RIC":13,"OCO":17,"NOR":3,"HAM":18,"SAI":1,"RUS":7,"BOT":15,"PIA":4}},{"lap":56,"positions":{"VER":19,"GAS":14,"PER":5,"ALO":6,"LEC":2,"STR":8,"MAG":11,"TSU":9,"ALB":12,"ZHO":16,"HUL":10,"RIC":13,"OCO":17,"NOR":3,"HAM":18,"SAI":1,"RUS":7,"BOT":15,"PIA":4}},{"lap":57,"positions":{"VER":19,"GAS":13,"PER":5,"ALO":6,"LEC":2,"STR":7,"MAG":10,"TSU":8,"ALB":11,"ZHO":15,"HUL":9,"RIC":12,"OCO":16,"NOR":3,"HAM":18,"SAI":1,"RUS":17,"BOT":14,"PIA":4}},{"lap":58,"positions":{"VER":19,"GAS":13,"PER":5,"ALO":8,"LEC":2,"STR":6,"MAG":10,"TSU":7,"ALB":11,"ZHO":15,"HUL":9,"RIC":12,"OCO":16,"NOR":3,"HAM":18,"SAI":1,"RUS":17,"BOT":14,"PIA":4}}],"dnfLaps":{"VER":4,"HAM":15,"RUS":56},"stints":{"VER":[{"startLap":1,"endLap":4,"compound":"MEDIUM"}],"GAS":[{"startLap":1,"endLap":17,"compound":"MEDIUM"},{"startLap":18,"endLap":57,"compound":"HARD"}],"PER":[{"startLap":1,"endLap":14,"compound":"MEDIUM"},{"startLap":15,"endLap":58,"compound":"HARD"}],"ALO":[{"startLap":1,"endLap":17,"compound":"HARD"},{"startLap":18,"endLap":41,"compound":"MEDIUM"},{"startLap":42,"endLap":58,"compound":"HARD"}],"LEC":[{"startLap":1,"endLap":9,"compound":"MEDIUM"},{"startLap":10,"endLap":58,"compound":"HARD"}],"STR":[{"startLap":1,"endLap":8,"compound":"MEDIUM"},{"startLap":9,"endLap":58,"compound":"HARD"}],"MAG":[{"startLap":1,"endLap":7,"compound":"MEDIUM"},{"startLap":8,"endLap":57,"compound":"HARD"}],"TSU":[{"startLap":1,"endLap":9,"compound":"MEDIUM"},{"startLap":10,"endLap":58,"compound":"HARD"}],"ALB":[{"startLap":1,"endLap":6,"compound":"MEDIUM"},{"startLap":7,"endLap":57,"compound":"HARD"}],"ZHO":[{"startLap":1,"endLap":6,"compound":"SOFT"},{"startLap":7,"endLap":57,"compound":"HARD"}],"HUL":[{"startLap":1,"endLap":17,"compound":"HARD"},{"startLap":18,"endLap":35,"compound":"MEDIUM"},{"startLap":36,"endLap":58,"compound":"HARD"}],"RIC":[{"startLap":1,"endLap":5,"compound":"SOFT"},{"startLap":6,"endLap":57,"compound":"HARD"}],"OCO":[{"startLap":1,"endLap":9,"compound":"MEDIUM"},{"startLap":10,"endLap":57,"compound":"HARD"}],"NOR":[{"startLap":1,"endLap":14,"compound":"MEDIUM"},{"startLap":15,"endLap":58,"compound":"HARD"}],"HAM":[{"startLap":1,"endLap":7,"compound":"SOFT"},{"startLap":8,"endLap":15,"compound":"HARD"}],"SAI":[{"startLap":1,"endLap":16,"compound":"MEDIUM"},{"startLap":17,"endLap":58,"compound":"HARD"}],"RUS":[{"startLap":1,"endLap":8,"compound":"MEDIUM"},{"startLap":9,"endLap":56,"compound":"HARD"}],"BOT":[{"startLap":1,"endLap":8,"compound":"MEDIUM"},{"startLap":9,"endLap":57,"compound":"HARD"}],"PIA":[{"startLap":1,"endLap":9,"compound":"MEDIUM"},{"startLap":10,"endLap":58,"compound":"HARD"}]},"safetyCars":[{"startLap":16,"endLap":18,"type":"VSC"},{"startLap":56,"endLap":58,"type":"VSC"}],"gapsByLap":[{"lap":1,"gaps":{"VER":0.0,"GAS":9.846,"PER":4.97,"ALO":7.045,"LEC":3.062,"STR":5.377,"MAG":8.009,"TSU":5.847,"ALB":8.294,"ZHO":11.233,"HUL":9.462,"RIC":10.187,"OCO":8.825,"NOR":2.326,"HAM":6.23,"SAI":0.917,"RUS":4.452,"BOT":7.305,"PIA":3.578}},{"lap":2,"gaps":{"VER":0.582,"GAS":10.978,"PER":4.834,"ALO":7.812,"LEC":2.559,"STR":5.411,"MAG":8.74,"TSU":6.137,"ALB":9.313,"ZHO":12.095,"HUL":10.652,"RIC":11.496,"OCO":9.988,"NOR":1.992,"HAM":6.768,"SAI":0.0,"RUS":4.282,"BOT":8.132,"PIA":3.293}},{"lap":3,"gaps":{"VER":0.691,"GAS":11.823,"PER":4.993,"ALO":7.784,"LEC":2.329,"STR":5.601,"MAG":9.299,"TSU":6.334,"ALB":9.913,"ZHO":13.001,"HUL":11.222,"RIC":12.33,"OCO":10.559,"NOR":1.642,"HAM":6.832,"SAI":0.0,"RUS":4.313,"BOT":8.398,"PIA":2.956}},{"lap":4,"gaps":{"VER":18.623,"GAS":13.09,"PER":5.958,"ALO":9.093,"LEC":2.415,"STR":6.622,"MAG":10.395,"TSU":7.335,"ALB":10.918,"ZHO":14.516,"HUL":12.52,"RIC":13.992,"OCO":11.7,"NOR":1.818,"HAM":7.835,"SAI":0.0,"RUS":5.451,"BOT":9.67,"PIA":3.104}},{"lap":5,"gaps":{"GAS":14.987,"PER":6.693,"ALO":9.758,"LEC":2.418,"STR":7.33,"MAG":11.727,"TSU":8.016,"ALB":12.205,"ZHO":16.048,"HUL":14.356,"RIC":30.169,"OCO":12.855,"NOR":1.874,"HAM":8.762,"SAI":0.0,"RUS":5.994,"BOT":10.601,"PIA":3.069}},{"lap":6,"gaps":{"GAS":16.327,"PER":7.145,"ALO":10.382,"LEC":2.519,"STR":7.785,"MAG":13.109,"TSU":8.889,"ALB":27.494,"ZHO":32.417,"HUL":15.531,"RIC":38.173,"OCO":14.124,"NOR":1.934,"HAM":9.355,"SAI":0.0,"RUS":6.541,"BOT":11.151,"PIA":3.079}},{"lap":7,"gaps":{"GAS":17.338,"PER":7.515,"ALO":10.743,"LEC":2.769,"STR":8.37,"MAG":28.62,"TSU":9.319,"ALB":33.507,"ZHO":41.151,"HUL":16.965,"RIC":39.779,"OCO":14.888,"NOR":2.244,"HAM":23.779,"SAI":0.0,"RUS":6.871,"BOT":12.455,"PIA":3.522}},{"lap":8,"gaps":{"GAS":18.914,"PER":8.26,"ALO":11.209,"LEC":3.449,"STR":23.429,"MAG":36.296,"TSU":10.397,"ALB":34.924,"ZHO":43.25,"HUL":18.5,"RIC":41.084,"OCO":15.565,"NOR":2.571,"HAM":29.64,"SAI":0.0,"RUS":21.488,"BOT":56.797,"PIA":4.271}},{"lap":9,"gaps":{"GAS":20.718,"PER":9.205,"ALO":12.529,"LEC":17.46,"STR":29.349,"MAG":37.933,"TSU":26.582,"ALB":36.544,"ZHO":44.849,"HUL":20.331,"RIC":42.55,"OCO":31.488,"NOR":3.273,"HAM":30.17,"SAI":0.0,"RUS":27.794,"BOT":64.691,"PIA":18.747}},{"lap":10,"gaps":{"GAS":22.859,"PER":10.17,"ALO":13.422,"LEC":23.606,"STR":30.517,"MAG":39.889,"TSU":34.759,"ALB":38.681,"ZHO":46.794,"HUL":22.393,"RIC":44.08,"OCO":39.212,"NOR":4.253,"HAM":32.75,"SAI":0.0,"RUS":28.816,"BOT":66.137,"PIA":24.831}},{"lap":11,"gaps":{"GAS":26.318,"PER":11.153,"ALO":14.423,"LEC":24.315,"STR":31.297,"MAG":41.273,"TSU":35.719,"ALB":39.997,"ZHO":48.303,"HUL":25.525,"RIC":45.225,"OCO":40.613,"NOR":5.251,"HAM":33.256,"SAI":0.0,"RUS":29.594,"BOT":67.639,"PIA":25.621}},{"lap":12,"gaps":{"GAS":28.768,"PER":12.682,"ALO":15.152,"LEC":23.981,"STR":32.185,"MAG":42.208,"TSU":36.343,"ALB":40.589,"ZHO":49.305,"HUL":28.174,"RIC":46.108,"OCO":41.32,"NOR":5.89,"HAM":34.122,"SAI":0.0,"RUS":30.441,"BOT":68.44,"PIA":26.394}},{"lap":13,"gaps":{"GAS":30.612,"PER":14.141,"ALO":16.134,"LEC":23.998,"STR":33.302,"MAG":43.066,"TSU":37.17,"ALB":41.567,"ZHO":50.571,"HUL":29.922,"RIC":46.807,"OCO":42.071,"NOR":6.838,"HAM":35.163,"SAI":0.0,"RUS":31.674,"BOT":69.394,"PIA":26.615}},{"lap":14,"gaps":{"GAS":32.229,"PER":30.347,"ALO":17.102,"LEC":23.463,"STR":33.921,"MAG":43.484,"TSU":37.506,"ALB":42.058,"ZHO":51.386,"HUL":31.4,"RIC":47.197,"OCO":42.703,"NOR":22.45,"HAM":35.388,"SAI":0.0,"RUS":32.577,"BOT":70.302,"PIA":26.096}},{"lap":15,"gaps":{"GAS":33.709,"PER":35.636,"ALO":17.62,"LEC":22.578,"STR":34.751,"MAG":44.532,"TSU":38.222,"ALB":42.465,"ZHO":52.095,"HUL":33.061,"RIC":47.407,"OCO":43.174,"NOR":28.035,"HAM":36.909,"SAI":0.0,"RUS":34.043,"BOT":71.011,"PIA":25.437}},{"lap":16,"gaps":{"GAS":22.766,"PER":23.448,"ALO":4.549,"LEC":8.515,"STR":23.091,"MAG":31.783,"TSU":25.164,"ALB":29.118,"ZHO":39.124,"HUL":20.776,"RIC":34.24,"OCO":57.529,"NOR":13.661,"HAM":90.599,"SAI":0.0,"RUS":21.099,"BOT":58.82,"PIA":11.142}},{"lap":17,"gaps":{"GAS":36.789,"PER":23.519,"ALO":9.393,"LEC":2.185,"STR":22.595,"MAG":32.894,"TSU":24.976,"ALB":29.659,"ZHO":40.273,"HUL":31.509,"RIC":35.381,"OCO":60.83,"NOR":8.284,"SAI":0.0,"RUS":18.819,"BOT":60.336,"PIA":4.199}},{"lap":18,"gaps":{"GAS":36.747,"PER":17.858,"ALO":10.186,"LEC":1.151,"STR":18.666,"MAG":26.089,"TSU":19.938,"ALB":24.073,"ZHO":35.301,"HUL":29.533,"RIC":30.568,"OCO":53.487,"NOR":5.772,"SAI":0.0,"RUS":16.055,"BOT":53.015,"PIA":3.263}},{"lap":19,"gaps":{"GAS":38.858,"PER":17.887,"ALO":11.303,"LEC":1.221,"STR":19.96,"MAG":27.126,"TSU":21.121,"ALB":25.284,"ZHO":37.027,"HUL":29.969,"RIC":31.781,"OCO":54.556,"NOR":6.317,"SAI":0.0,"RUS":16.644,"BOT":53.801,"PIA":3.323}},{"lap":20,"gaps":{"GAS":40.918,"PER":17.996,"ALO":12.532,"LEC":1.504,"STR":21.28,"MAG":28.333,"TSU":22.567,"ALB":26.289,"ZHO":38.494,"HUL":30.773,"RIC":33.306,"OCO":55.768,"NOR":6.357,"SAI":0.0,"RUS":17.476,"BOT":54.893,"PIA":3.806}},{"lap":21,"gaps":{"GAS":42.228,"PER":18.116,"ALO":13.305,"LEC":1.631,"STR":21.977,"MAG":29.262,"TSU":23.604,"ALB":27.424,"ZHO":40.036,"HUL":31.321,"RIC":34.562,"OCO":56.5,"NOR":6.333,"SAI":0.0,"RUS":18.974,"BOT":55.401,"PIA":3.798}},{"lap":22,"gaps":{"GAS":43.802,"PER":18.514,"ALO":14.312,"LEC":1.882,"STR":23.411,"MAG":31.106,"TSU":24.806,"ALB":29.254,"ZHO":41.996,"HUL":32.289,"RIC":36.196,"OCO":57.832,"NOR":6.611,"SAI":0.0,"RUS":20.341,"BOT":56.652,"PIA":4.34}},{"lap":23,"gaps":{"GAS":45.2,"PER":18.832,"ALO":15.222,"LEC":2.283,"STR":24.741,"MAG":33.86,"TSU":26.228,"ALB":30.921,"ZHO":43.729,"HUL":32.91,"RIC":37.677,"OCO":59.014,"NOR":6.825,"SAI":0.0,"RUS":21.822,"BOT":57.461,"PIA":4.626}},{"lap":24,"gaps":{"GAS":46.743,"PER":18.901,"ALO":16.051,"LEC":2.677,"STR":26.135,"MAG":35.732,"TSU":27.796,"ALB":32.976,"ZHO":45.467,"HUL":33.98,"RIC":39.511,"OCO":60.315,"NOR":6.929,"SAI":0.0,"RUS":23.306,"BOT":58.913,"PIA":4.998}},{"lap":25,"gaps":{"GAS":48.433,"PER":19.153,"ALO":17.516,"LEC":3.385,"STR":27.833,"MAG":37.991,"TSU":29.554,"ALB":35.404,"ZHO":47.255,"HUL":35.711,"RIC":41.815,"OCO":61.869,"NOR":7.399,"SAI":0.0,"RUS":24.766,"BOT":60.221,"PIA":5.352}},{"lap":26,"gaps":{"GAS":50.37,"PER":20.321,"ALO":19.426,"LEC":4.349,"STR":30.049,"MAG":40.398,"TSU":31.778,"ALB":37.851,"ZHO":49.239,"HUL":38.326,"RIC":44.094,"OCO":63.683,"NOR":7.932,"SAI":0.0,"RUS":26.573,"BOT":62.21,"PIA":6.517}},{"lap":27,"gaps":{"GAS":51.817,"PER":20.421,"ALO":21.226,"LEC":4.714,"STR":31.784,"MAG":42.466,"TSU":33.569,"ALB":53.834,"ZHO":50.879,"HUL":40.254,"RIC":46.522,"OCO":65.127,"NOR":8.451,"SAI":0.0,"RUS":28.254,"BOT":63.687,"PIA":7.347}},{"lap":28,"gaps":{"GAS":53.051,"PER":21.133,"ALO":22.045,"LEC":5.243,"STR":33.403,"MAG":44.493,"TSU":35.204,"ALB":61.603,"ZHO":52.462,"HUL":42.152,"RIC":48.945,"OCO":66.795,"NOR":8.848,"SAI":0.0,"RUS":29.91,"BOT":65.195,"PIA":8.111}},{"lap":29,"gaps":{"GAS":54.27,"PER":21.77,"ALO":22.536,"LEC":6.187,"STR":35.049,"MAG":46.46,"TSU":37.213,"ALB":62.906,"ZHO":53.575,"HUL":43.83,"RIC":64.797,"OCO":68.423,"NOR":9.223,"SAI":0.0,"RUS":31.084,"BOT":66.541,"PIA":10.101}},{"lap":30,"gaps":{"GAS":55.637,"PER":22.327,"ALO":23.088,"LEC":6.848,"STR":36.55,"MAG":48.244,"TSU":38.972,"ALB":64.181,"ZHO":54.941,"HUL":45.506,"RIC":73.776,"OCO":69.84,"NOR":9.582,"SAI":0.0,"RUS":32.124,"BOT":67.916,"PIA":10.998}},{"lap":31,"gaps":{"GAS":57.082,"PER":23.404,"ALO":24.161,"LEC":7.562,"STR":38.789,"MAG":50.178,"TSU":41.057,"ALB":65.848,"ZHO":56.485,"HUL":47.363,"RIC":75.432,"OCO":71.479,"NOR":10.148,"SAI":0.0,"RUS":33.357,"BOT":69.644,"PIA":11.849}},{"lap":32,"gaps":{"GAS":59.122,"PER":24.64,"ALO":25.447,"LEC":8.198,"STR":40.741,"MAG":52.369,"TSU":43.242,"ALB":67.544,"ZHO":58.45,"HUL":49.05,"RIC":76.965,"OCO":73.183,"NOR":10.517,"SAI":0.0,"RUS":34.862,"BOT":71.336,"PIA":12.633}},{"lap":33,"gaps":{"GAS":60.842,"PER":25.711,"ALO":26.601,"LEC":8.725,"STR":42.512,"MAG":68.676,"TSU":44.973,"ALB":69.237,"ZHO":60.201,"HUL":50.465,"RIC":77.913,"OCO":74.684,"NOR":10.714,"SAI":0.0,"RUS":35.828,"BOT":72.692,"PIA":13.238}},{"lap":34,"gaps":{"GAS":62.161,"PER":26.956,"ALO":27.802,"LEC":22.97,"STR":43.909,"MAG":75.498,"TSU":46.579,"ALB":70.581,"ZHO":61.552,"HUL":51.891,"RIC":78.905,"OCO":78.45,"NOR":10.766,"SAI":0.0,"RUS":36.464,"BOT":77.428,"PIA":13.759}},{"lap":35,"gaps":{"GAS":63.665,"PER":44.675,"ALO":31.811,"LEC":29.2,"STR":45.586,"MAG":76.117,"TSU":48.147,"ALB":71.995,"ZHO":96.426,"HUL":67.484,"RIC":80.674,"OCO":79.968,"NOR":10.555,"SAI":0.0,"RUS":37.334,"BOT":79.153,"PIA":14.097}},{"lap":36,"gaps":{"GAS":64.487,"PER":50.329,"ALO":32.507,"LEC":29.124,"STR":46.775,"MAG":76.208,"TSU":63.285,"ALB":74.463,"ZHO":102.978,"HUL":72.766,"RIC":83.787,"OCO":82.89,"NOR":9.983,"SAI":0.0,"RUS":37.853,"BOT":95.658,"PIA":14.126}},{"lap":37,"gaps":{"GAS":65.842,"PER":49.576,"ALO":33.398,"LEC":27.841,"STR":62.33,"MAG":76.498,"TSU":70.458,"ALB":75.41,"ZHO":103.605,"HUL":72.425,"RIC":84.254,"OCO":83.753,"NOR":9.674,"SAI":0.0,"RUS":38.29,"BOT":101.841,"PIA":14.045}},{"lap":38,"gaps":{"GAS":69.539,"PER":49.409,"ALO":34.552,"LEC":27.378,"STR":68.765,"MAG":77.171,"TSU":70.97,"ALB":76.152,"ZHO":104.623,"HUL":73.038,"RIC":85.222,"OCO":85.968,"NOR":9.78,"SAI":0.0,"RUS":39.053,"BOT":102.184,"PIA":17.836}},{"lap":39,"gaps":{"GAS":71.001,"PER":49.303,"ALO":35.77,"LEC":26.733,"STR":69.253,"MAG":77.462,"TSU":71.663,"ALB":76.609,"ZHO":105.077,"HUL":73.38,"RIC":85.84,"OCO":87.12,"NOR":10.127,"SAI":0.0,"RUS":39.666,"BOT":102.276,"PIA":33.063}},{"lap":40,"gaps":{"GAS":74.578,"PER":48.905,"ALO":37.041,"LEC":26.243,"STR":69.91,"MAG":77.79,"TSU":73.438,"ALB":76.906,"ZHO":105.542,"HUL":74.76,"RIC":85.784,"OCO":88.666,"NOR":24.707,"SAI":0.0,"RUS":40.696,"BOT":102.366,"PIA":38.55}},{"lap":41,"gaps":{"GAS":83.662,"PER":34.393,"ALO":40.519,"LEC":11.408,"STR":56.644,"MAG":65.469,"TSU":59.692,"ALB":64.97,"ZHO":94.031,"HUL":61.266,"RIC":71.882,"OCO":76.318,"NOR":15.773,"SAI":0.0,"RUS":27.505,"BOT":88.864,"PIA":24.464}},{"lap":42,"gaps":{"GAS":84.618,"PER":28.528,"ALO":40.651,"LEC":5.042,"STR":51.258,"MAG":60.168,"TSU":54.261,"ALB":59.485,"ZHO":89.011,"HUL":56.224,"RIC":66.555,"OCO":87.301,"NOR":9.583,"SAI":0.0,"RUS":22.547,"BOT":86.829,"PIA":18.329}},{"lap":43,"gaps":{"GAS":88.307,"PER":28.596,"ALO":41.645,"LEC":5.165,"STR":52.25,"MAG":61.491,"TSU":55.459,"ALB":61.047,"ZHO":92.108,"HUL":57.403,"RIC":67.473,"OCO":94.777,"NOR":9.505,"SAI":0.0,"RUS":23.928,"BOT":88.988,"PIA":18.084}},{"lap":44,"gaps":{"GAS":88.987,"PER":28.535,"ALO":42.272,"LEC":4.958,"STR":53.475,"MAG":61.806,"TSU":56.516,"ALB":62.779,"ZHO":93.488,"HUL":58.366,"RIC":68.019,"OCO":95.607,"NOR":9.351,"SAI":0.0,"RUS":25.258,"BOT":91.462,"PIA":17.712}},{"lap":45,"gaps":{"GAS":90.843,"PER":29.081,"ALO":43.503,"LEC":5.143,"STR":54.855,"MAG":63.22,"TSU":57.989,"ALB":64.463,"ZHO":94.874,"HUL":59.675,"RIC":69.126,"OCO":96.738,"NOR":9.748,"SAI":0.0,"RUS":41.378,"BOT":92.95,"PIA":17.712}},{"lap":46,"gaps":{"GAS":91.689,"PER":29.135,"ALO":44.473,"LEC":5.529,"STR":55.912,"MAG":64.309,"TSU":58.749,"ALB":65.707,"ZHO":96.163,"HUL":60.446,"RIC":69.991,"OCO":99.405,"NOR":9.345,"SAI":0.0,"RUS":47.438,"BOT":94.13,"PIA":17.953}},{"lap":47,"gaps":{"GAS":92.761,"PER":29.32,"ALO":45.453,"LEC":5.325,"STR":56.723,"MAG":65.644,"TSU":59.8,"ALB":67.349,"ZHO":97.736,"HUL":61.872,"RIC":71.088,"OCO":100.666,"NOR":9.33,"SAI":0.0,"RUS":47.561,"BOT":95.51,"PIA":18.432}},{"lap":48,"gaps":{"GAS":93.941,"PER":30.125,"ALO":46.769,"LEC":5.643,"STR":57.801,"MAG":67.283,"TSU":60.943,"ALB":69.245,"ZHO":100.84,"HUL":63.443,"RIC":72.549,"OCO":102.184,"NOR":9.559,"SAI":0.0,"RUS":48.269,"BOT":96.901,"PIA":18.989}},{"lap":49,"gaps":{"GAS":95.0,"PER":30.604,"ALO":47.61,"LEC":5.506,"STR":58.45,"MAG":68.388,"TSU":61.965,"ALB":70.882,"ZHO":101.886,"HUL":64.89,"RIC":73.874,"OCO":103.581,"NOR":9.193,"SAI":0.0,"RUS":48.796,"BOT":98.077,"PIA":19.06}},{"lap":50,"gaps":{"GAS":95.772,"PER":31.025,"ALO":47.896,"LEC":4.981,"STR":58.991,"MAG":69.604,"TSU":62.8,"ALB":72.651,"ZHO":103.267,"HUL":66.542,"RIC":75.206,"OCO":104.764,"NOR":8.894,"SAI":0.0,"RUS":49.328,"BOT":101.525,"PIA":19.106}},{"lap":51,"gaps":{"GAS":96.779,"PER":31.98,"ALO":48.751,"LEC":5.113,"STR":60.029,"MAG":70.941,"TSU":64.285,"ALB":74.887,"ZHO":105.014,"HUL":68.189,"RIC":76.892,"OCO":106.632,"NOR":9.072,"SAI":0.0,"RUS":49.94,"BOT":103.091,"PIA":19.741}},{"lap":52,"gaps":{"GAS":97.731,"PER":32.921,"ALO":49.035,"LEC":5.235,"STR":61.033,"MAG":72.363,"TSU":65.723,"ALB":76.862,"ZHO":106.865,"HUL":69.761,"RIC":78.567,"OCO":108.578,"NOR":8.822,"SAI":0.0,"RUS":50.26,"BOT":104.938,"PIA":19.827}},{"lap":53,"gaps":{"GAS":98.44,"PER":33.85,"ALO":49.287,"LEC":5.083,"STR":61.481,"MAG":73.411,"TSU":66.661,"ALB":78.646,"ZHO":108.434,"HUL":70.904,"RIC":82.184,"OCO":110.17,"NOR":8.474,"SAI":0.0,"RUS":49.929,"BOT":106.143,"PIA":19.52}},{"lap":54,"gaps":{"GAS":100.892,"PER":34.898,"ALO":49.74,"LEC":4.821,"STR":62.029,"MAG":78.084,"TSU":67.795,"ALB":82.195,"ZHO":109.919,"HUL":72.343,"RIC":84.17,"OCO":111.817,"NOR":7.999,"SAI":0.0,"RUS":50.541,"BOT":107.59,"PIA":19.137}},{"lap":55,"gaps":{"GAS":101.566,"PER":35.761,"ALO":49.939,"LEC":5.03,"STR":62.548,"MAG":82.282,"TSU":68.719,"ALB":83.754,"ZHO":110.964,"HUL":74.287,"RIC":87.028,"OCO":113.368,"NOR":7.54,"SAI":0.0,"RUS":50.579,"BOT":108.847,"PIA":19.138}},{"lap":56,"gaps":{"GAS":107.379,"PER":36.512,"ALO":49.593,"LEC":3.745,"STR":62.683,"MAG":84.382,"TSU":69.433,"ALB":86.846,"ZHO":117.924,"HUL":75.463,"RIC":89.769,"OCO":122.077,"NOR":6.923,"SAI":0.0,"RUS":50.136,"BOT":115.799,"PIA":18.397}},{"lap":57,"gaps":{"GAS":147.316,"PER":45.93,"ALO":63.894,"LEC":3.734,"STR":84.818,"MAG":115.444,"TSU":92.922,"ALB":116.372,"ZHO":155.656,"HUL":106.684,"RIC":122.871,"OCO":165.342,"NOR":6.612,"SAI":0.0,"RUS":119.254,"BOT":153.689,"PIA":22.77}},{"lap":58,"gaps":{"PER":56.309,"ALO":80.992,"LEC":2.366,"STR":93.222,"TSU":95.601,"HUL":104.553,"NOR":5.904,"SAI":0.0,"PIA":35.77}}],"fastestLap":{"driver":"LEC","lap":56,"time":"1:19.813"}}