{"positionsByLap":[{"lap":1,"positions":{"VER":4,"GAS":18,"ANT":14,"ALO":6,"LEC":2,"STR":16,"TSU":17,"ALB":10,"HUL":12,"LAW":9,"OCO":8,"NOR":1,"COL":15,"HAM":7,"BOR":20,"SAI":11,"HAD":5,"RUS":13,"PIA":3,"BEA":19}},{"lap":2,"positions":{"VER":4,"GAS":18,"ANT":14,"ALO":6,"LEC":2,"STR":16,"TSU":17,"ALB":10,"HUL":12,"LAW":9,"OCO":8,"NOR":1,"COL":15,"HAM":7,"BOR":20,"SAI":11,"HAD":5,"RUS":13,"PIA":3,"BEA":19}},{"lap":3,"positions":{"VER":4,"GAS":18,"ANT":14,"ALO":6,"LEC":2,"STR":16,"TSU":17,"ALB":10,"HUL":12,"LAW":9,"OCO":8,"NOR":1,"COL":15,"HAM":7,"BOR":20,"SAI":11,"HAD":5,"RUS":13,"PIA":3,"BEA":19}},{"lap":4,"positions":{"VER":4,"GAS":18,"ANT":14,"ALO":6,"LEC":2,"STR":16,"TSU":17,"ALB":10,"HUL":12,"LAW":9,"OCO":8,"NOR":1,"COL":15,"HAM":7,"BOR":20,"SAI":11,"HAD":5,"RUS":13,"PIA":3,"BEA":19}},{"lap":5,"positions":{"VER":4,"GAS":18,"ANT":14,"ALO":6,"LEC":2,"STR":16,"TSU":17,"ALB":10,"HUL":12,"LAW":9,"OCO":8,"NOR":1,"COL":15,"HAM":7,"BOR":20,"SAI":11,"HAD":5,"RUS":13,"PIA":3,"BEA":19}},{"lap":6,"positions":{"VER":4,"GAS":18,"ANT":14,"ALO":6,"LEC":2,"STR":16,"TSU":17,"ALB":10,"HUL":12,"LAW":9,"OCO":8,"NOR":1,"COL":15,"HAM":7,"BOR":20,"SAI":11,"HAD":5,"RUS":13,"PIA":3,"BEA":19}},{"lap":7,"positions":{"VER":4,"GAS":18,"ANT":14,"ALO":6,"LEC":2,"STR":16,"TSU":17,"ALB":10,"HUL":12,"LAW":9,"OCO":8,"NOR":1,"COL":15,"HAM":7,"BOR":20,"SAI":11,"HAD":5,"RUS":13,"PIA":3,"BEA":19}},{"lap":8,"positions":{"VER":4,"GAS":19,"ANT":14,"ALO":6,"LEC":2,"STR":16,"TSU":17,"ALB":10,"HUL":12,"LAW":9,"OCO":8,"NOR":1,"COL":15,"HAM":7,"BOR":20,"SAI":11,"HAD":5,"RUS":13,"PIA":3,"BEA":18}},{"lap":9,"positions":{"VER":4,"GAS":20,"ANT":14,"ALO":6,"LEC":2,"STR":16,"TSU":17,"ALB":10,"HUL":12,"LAW":9,"OCO":8,"NOR":1,"COL":15,"HAM":7,"BOR":19,"SAI":11,"HAD":5,"RUS":13,"PIA":3,"BEA":18}},{"lap":10,"positions":{"VER":4,"GAS":20,"ANT":14,"ALO":6,"LEC":2,"STR":16,"TSU":17,"ALB":10,"HUL":12,"LAW":9,"OCO":8,"NOR":1,"COL":15,"HAM":7,"BOR":19,"SAI":11,"HAD":5,"RUS":13,"PIA":3,"BEA":18}},{"lap":11,"positions":{"VER":4,"GAS":20,"ANT":14,"ALO":6,"LEC":2,"STR":16,"TSU":17,"ALB":10,"HUL":12,"LAW":9,"OCO":8,"NOR":1,"COL":15,"HAM":7,"BOR":19,"SAI":11,"HAD":5,"RUS":13,"PIA":3,"BEA":18}},{"lap":12,"positions":{"VER":4,"GAS":20,"ANT":13,"ALO":6,"LEC":2,"STR":15,"TSU":16,"ALB":10,"HUL":19,"LAW":9,"OCO":8,"NOR":1,"COL":14,"HAM":7,"BOR":18,"SAI":11,"HAD":5,"RUS":12,"PIA":3,"BEA":17}},{"lap":13,"positions":{"VER":4,"GAS":20,"ANT":13,"ALO":6,"LEC":2,"STR":14,"TSU":15,"ALB":10,"HUL":18,"LAW":9,"OCO":8,"NOR":1,"COL":19,"HAM":7,"BOR":17,"SAI":11,"HAD":5,"RUS":12,"PIA":3,"BEA":16}},{"lap":14,"positions":{"VER":4,"GAS":20,"ANT":13,"ALO":5,"LEC":2,"STR":14,"TSU":15,"ALB":10,"HUL":18,"LAW":9,"OCO":7,"NOR":1,"COL":19,"HAM":6,"BOR":17,"SAI":11,"HAD":8,"RUS":12,"PIA":3,"BEA":16}},{"lap":15,"positions":{"VER":4,"GAS":20,"ANT":13,"ALO":5,"LEC":2,"STR":14,"TSU":15,"ALB":10,"HUL":18,"LAW":9,"OCO":7,"NOR":1,"COL":19,"HAM":6,"BOR":17,"SAI":11,"HAD":8,"RUS":12,"PIA":3,"BEA":16}},{"lap":16,"positions":{"VER":4,"GAS":20,"ANT":13,"ALO":6,"LEC":2,"STR":14,"TSU":15,"ALB":10,"HUL":18,"LAW":9,"OCO":8,"NOR":1,"COL":19,"HAM":5,"BOR":17,"SAI":11,"HAD":7,"RUS":12,"PIA":3,"BEA":16}},{"lap":17,"positions":{"VER":4,"GAS":20,"ANT":13,"ALO":7,"LEC":2,"STR":18,"TSU":14,"ALB":10,"HUL":16,"LAW":9,"OCO":8,"NOR":1,"COL":17,"HAM":5,"BOR":15,"SAI":11,"HAD":6,"RUS":12,"PIA":3,"BEA":19}},{"lap":18,"positions":{"VER":4,"GAS":20,"ANT":13,"ALO":7,"LEC":2,"STR":18,"TSU":14,"ALB":10,"HUL":16,"LAW":9,"OCO":8,"NOR":1,"COL":17,"HAM":5,"BOR":15,"SAI":11,"HAD":6,"RUS":12,"PIA":3,"BEA":19}},{"lap":19,"positions":{"VER":3,"GAS":20,"ANT":13,"ALO":6,"LEC":1,"STR":18,"TSU":14,"ALB":10,"HUL":16,"LAW":9,"OCO":7,"NOR":4,"COL":17,"HAM":5,"BOR":15,"SAI":11,"HAD":8,"RUS":12,"PIA":2,"BEA":19}},{"lap":20,"positions":{"VER":2,"GAS":20,"ANT":13,"ALO":6,"LEC":1,"STR":18,"TSU":14,"ALB":10,"HUL":16,"LAW":9,"OCO":7,"NOR":3,"COL":17,"HAM":5,"BOR":15,"SAI":11,"HAD":8,"RUS":12,"PIA":4,"BEA":19}},{"lap":21,"positions":{"VER":2,"GAS":20,"ANT":13,"ALO":6,"LEC":1,"STR":18,"TSU":14,"ALB":10,"HUL":16,"LAW":9,"OCO":7,"NOR":3,"COL":17,"HAM":5,"BOR":15,"SAI":11,"HAD":8,"RUS":12,"PIA":4,"BEA":19}},{"lap":22,"positions":{"VER":1,"GAS":20,"ANT":13,"ALO":6,"LEC":3,"STR":18,"TSU":14,"ALB":10,"HUL":16,"LAW":9,"OCO":7,"NOR":2,"COL":17,"HAM":5,"BOR":15,"SAI":11,"HAD":8,"RUS":12,"PIA":4,"BEA":19}},{"lap":23,"positions":{"VER":1,"GAS":20,"ANT":13,"ALO":6,"LEC":3,"STR":18,"TSU":14,"ALB":10,"HUL":16,"LAW":9,"OCO":7,"NOR":2,"COL":17,"HAM":5,"BOR":15,"SAI":11,"HAD":8,"RUS":12,"PIA":4,"BEA":19}},{"lap":24,"positions":{"VER":1,"GAS":20,"ANT":13,"ALO":6,"LEC":3,"STR":18,"TSU":14,"ALB":10,"HUL":16,"LAW":9,"OCO":7,"NOR":2,"COL":17,"HAM":5,"BOR":15,"SAI":11,"HAD":8,"RUS":12,"PIA":4,"BEA":19}},{"lap":25,"positions":{"VER":1,"GAS":20,"ANT":13,"ALO":6,"LEC":3,"STR":18,"TSU":14,"ALB":10,"HUL":16,"LAW":9,"OCO":7,"NOR":2,"COL":17,"HAM":5,"BOR":15,"SAI":11,"HAD":8,"RUS":12,"PIA":4,"BEA":19}},{"lap":26,"positions":{"VER":1,"GAS":20,"ANT":13,"ALO":6,"LEC":3,"STR":16,"TSU":14,"ALB":10,"HUL":15,"LAW":9,"OCO":7,"NOR":2,"COL":19,"HAM":5,"BOR":18,"SAI":11,"HAD":8,"RUS":12,"PIA":4,"BEA":17}},{"lap":27,"positions":{"VER":1,"GAS":20,"ANT":13,"ALO":6,"LEC":3,"STR":16,"TSU":14,"ALB":10,"HUL":15,"LAW":9,"OCO":7,"NOR":2,"COL":19,"HAM":5,"BOR":18,"SAI":11,"HAD":8,"RUS":12,"PIA":4,"BEA":17}},{"lap":28,"positions":{"VER":4,"GAS":20,"ANT":13,"ALO":6,"LEC":2,"STR":16,"TSU":14,"ALB":9,"HUL":15,"LAW":8,"OCO":10,"NOR":1,"COL":19,"HAM":5,"BOR":18,"SAI":11,"HAD":7,"RUS":12,"PIA":3,"BEA":17}},{"lap":29,"positions":{"VER":4,"GAS":20,"ANT":13,"ALO":6,"LEC":2,"STR":16,"TSU":14,"ALB":9,"HUL":15,"LAW":8,"OCO":10,"NOR":1,"COL":19,"HAM":5,"BOR":18,"SAI":11,"HAD":7,"RUS":12,"PIA":3,"BEA":17}},{"lap":30,"positions":{"VER":4,"GAS":20,"ANT":13,"ALO":6,"LEC":2,"STR":16,"TSU":14,"ALB":9,"HUL":15,"LAW":8,"OCO":10,"NOR":1,"COL":19,"HAM":5,"BOR":18,"SAI":11,"HAD":7,"RUS":12,"PIA":3,"BEA":17}},{"lap":31,"positions":{"VER":4,"GAS":20,"ANT":13,"ALO":6,"LEC":2,"STR":16,"TSU":14,"ALB":8,"HUL":15,"LAW":10,"OCO":9,"NOR":1,"COL":19,"HAM":5,"BOR":18,"SAI":11,"HAD":7,"RUS":12,"PIA":3,"BEA":17}},{"lap":32,"positions":{"VER":4,"GAS":20,"ANT":13,"ALO":6,"LEC":2,"STR":16,"TSU":14,"ALB":9,"HUL":15,"LAW":10,"OCO":8,"NOR":1,"COL":19,"HAM":5,"BOR":18,"SAI":11,"HAD":7,"RUS":12,"PIA":3,"BEA":17}},{"lap":33,"positions":{"VER":4,"GAS":20,"ANT":13,"ALO":6,"LEC":2,"STR":16,"TSU":14,"ALB":10,"HUL":15,"LAW":9,"OCO":8,"NOR":1,"COL":19,"HAM":5,"BOR":18,"SAI":11,"HAD":7,"RUS":12,"PIA":3,"BEA":17}},{"lap":34,"positions":{"VER":4,"GAS":20,"ANT":13,"ALO":6,"LEC":2,"STR":16,"TSU":14,"ALB":10,"HUL":15,"LAW":9,"OCO":8,"NOR":1,"COL":19,"HAM":5,"BOR":18,"SAI":11,"HAD":7,"RUS":12,"PIA":3,"BEA":17}},{"lap":35,"positions":{"VER":4,"GAS":20,"ANT":13,"ALO":6,"LEC":2,"STR":16,"TSU":14,"ALB":10,"HUL":15,"LAW":9,"OCO":8,"NOR":1,"COL":18,"HAM":5,"BOR":19,"SAI":11,"HAD":7,"RUS":12,"PIA":3,"BEA":17}},{"lap":36,"positions":{"VER":4,"GAS":20,"ANT":13,"ALO":6,"LEC":2,"STR":16,"TSU":14,"ALB":10,"HUL":15,"LAW":9,"OCO":8,"NOR":1,"COL":18,"HAM":5,"BOR":19,"SAI":11,"HAD":7,"RUS":12,"PIA":3,"BEA":17}},{"lap":37,"positions":{"VER":4,"GAS":20,"ANT":12,"ALO":19,"LEC":2,"STR":15,"TSU":13,"ALB":9,"HUL":14,"LAW":8,"OCO":7,"NOR":1,"COL":17,"HAM":5,"BOR":18,"SAI":10,"HAD":6,"RUS":11,"PIA":3,"BEA":16}},{"lap":38,"positions":{"VER":4,"GAS":20,"ANT":12,"ALO":19,"LEC":2,"STR":15,"TSU":13,"ALB":9,"HUL":14,"LAW":8,"OCO":7,"NOR":1,"COL":17,"HAM":5,"BOR":18,"SAI":10,"HAD":6,"RUS":11,"PIA":3,"BEA":16}},{"lap":39,"positions":{"VER":4,"GAS":20,"ANT":12,"ALO":19,"LEC":2,"STR":15,"TSU":13,"ALB":9,"HUL":14,"LAW":8,"OCO":7,"NOR":1,"COL":17,"HAM":5,"BOR":18,"SAI":10,"HAD":6,"RUS":11,"PIA":3,"BEA":16}},{"lap":40,"positions":{"VER":4,"GAS":20,"ANT":12,"ALO":19,"LEC":2,"STR":15,"TSU":13,"ALB":9,"HUL":14,"LAW":8,"OCO":7,"NOR":1,"COL":17,"HAM":5,"BOR":18,"SAI":10,"HAD":6,"RUS":11,"PIA":3,"BEA":16}},{"lap":41,"positions":{"VER":4,"GAS":20,"ANT":12,"ALO":19,"LEC":2,"STR":15,"TSU":13,"ALB":9,"HUL":14,"LAW":8,"OCO":7,"NOR":1,"COL":17,"HAM":5,"BOR":18,"SAI":10,"HAD":6,"RUS":11,"PIA":3,"BEA":16}},{"lap":42,"positions":{"VER":4,"GAS":20,"ANT":12,"ALO":19,"LEC":2,"STR":15,"TSU":13,"ALB":10,"HUL":14,"LAW":8,"OCO":7,"NOR":1,"COL":17,"HAM":5,"BOR":18,"SAI":9,"HAD":6,"RUS":11,"PIA":3,"BEA":16}},{"lap":43,"positions":{"VER":4,"GAS":20,"ANT":12,"ALO":19,"LEC":2,"STR":15,"TSU":13,"ALB":10,"HUL":14,"LAW":8,"OCO":7,"NOR":1,"COL":17,"HAM":5,"BOR":18,"SAI":9,"HAD":6,"RUS":11,"PIA":3,"BEA":16}},{"lap":44,"positions":{"VER":4,"GAS":20,"ANT":12,"ALO":19,"LEC":2,"STR":14,"TSU":13,"ALB":10,"HUL":18,"LAW":8,"OCO":7,"NOR":1,"COL":16,"HAM":5,"BOR":17,"SAI":9,"HAD":6,"RUS":11,"PIA":3,"BEA":15}},{"lap":45,"positions":{"VER":4,"GAS":20,"ANT":12,"ALO":19,"LEC":2,"STR":14,"TSU":13,"ALB":10,"HUL":18,"LAW":8,"OCO":7,"NOR":1,"COL":16,"HAM":5,"BOR":17,"SAI":9,"HAD":6,"RUS":11,"PIA":3,"BEA":15}},{"lap":46,"positions":{"VER":4,"GAS":20,"ANT":12,"ALO":19,"LEC":2,"STR":14,"TSU":13,"ALB":10,"HUL":18,"LAW":8,"OCO":7,"NOR":1,"COL":16,"HAM":5,"BOR":17,"SAI":9,"HAD":6,"RUS":11,"PIA":3,"BEA":15}},{"lap":47,"positions":{"VER":4,"GAS":20,"ANT":12,"ALO":19,"LEC":2,"STR":14,"TSU":13,"ALB":10,"HUL":18,"LAW":8,"OCO":7,"NOR":1,"COL":16,"HAM":5,"BOR":17,"SAI":9,"HAD":6,"RUS":11,"PIA":3,"BEA":15}},{"lap":48,"positions":{"VER":3,"GAS":20,"ANT":12,"ALO":19,"LEC":2,"STR":14,"TSU":13,"ALB":11,"HUL":18,"LAW":8,"OCO":7,"NOR":1,"COL":16,"HAM":5,"BOR":17,"SAI":9,"HAD":6,"RUS":10,"PIA":4,"BEA":15}},{"lap":49,"positions":{"VER":2,"GAS":20,"ANT":12,"ALO":19,"LEC":3,"STR":14,"TSU":13,"ALB":11,"HUL":18,"LAW":8,"OCO":7,"NOR":1,"COL":16,"HAM":5,"BOR":17,"SAI":9,"HAD":6,"RUS":10,"PIA":4,"BEA":15}},{"lap":50,"positions":{"VER":1,"GAS":20,"ANT":12,"ALO":19,"LEC":3,"STR":14,"TSU":13,"ALB":11,"HUL":18,"LAW":8,"OCO":7,"NOR":2,"COL":16,"HAM":5,"BOR":17,"SAI":9,"HAD":6,"RUS":10,"PIA":4,"BEA":15}},{"lap":51,"positions":{"VER":1,"GAS":20,"ANT":12,"ALO":19,"LEC":3,"STR":14,"TSU":13,"ALB":11,"HUL":18,"LAW":8,"OCO":7,"NOR":2,"COL":16,"HAM":5,"BOR":17,"SAI":9,"HAD":6,"RUS":10,"PIA":4,"BEA":15}},{"lap":52,"positions":{"VER":1,"GAS":20,"ANT":12,"ALO":19,"LEC":3,"STR":14,"TSU":13,"ALB":11,"HUL":18,"LAW":8,"OCO":7,"NOR":2,"COL":16,"HAM":5,"BOR":17,"SAI":9,"HAD":6,"RUS":10,"PIA":4,"BEA":15}},{"lap":53,"positions":{"VER":1,"GAS":20,"ANT":12,"ALO":19,"LEC":3,"STR":14,"TSU":13,"ALB":11,"HUL":18,"LAW":8,"OCO":7,"NOR":2,"COL":16,"HAM":5,"BOR":17,"SAI":9,"HAD":6,"RUS":10,"PIA":4,"BEA":15}},{"lap":54,"positions":{"VER":1,"GAS":20,"ANT":12,"ALO":19,"LEC":3,"STR":14,"TSU":13,"ALB":11,"HUL":18,"LAW":8,"OCO":7,"NOR":2,"COL":16,"HAM":5,"BOR":17,"SAI":9,"HAD":6,"RUS":10,"PIA":4,"BEA":15}},{"lap":55,"positions":{"VER":1,"GAS":20,"ANT":12,"ALO":19,"LEC":3,"STR":14,"TSU":13,"ALB":11,"HUL":18,"LAW":8,"OCO":7,"NOR":2,"COL":16,"HAM":5,"BOR":17,"SAI":9,"HAD":6,"RUS":10,"PIA":4,"BEA":15}},{"lap":56,"positions":{"VER":1,"GAS":20,"ANT":12,"ALO":19,"LEC":3,"STR":14,"TSU":13,"ALB":11,"HUL":18,"LAW":8,"OCO":7,"NOR":2,"COL":16,"HAM":5,"BOR":17,"SAI":9,"HAD":6,"RUS":10,"PIA":4,"BEA":15}},{"lap":57,"positions":{"VER":1,"GAS":20,"ANT":12,"ALO":19,"LEC":3,"STR":14,"TSU":13,"ALB":11,"HUL":18,"LAW":8,"OCO":7,"NOR":2,"COL":16,"HAM":5,"BOR":17,"SAI":9,"HAD":6,"RUS":10,"PIA":4,"BEA":15}},{"lap":58,"positions":{"VER":1,"GAS":20,"ANT":12,"ALO":19,"LEC":3,"STR":14,"TSU":13,"ALB":11,"HUL":18,"LAW":8,"OCO":7,"NOR":2,"COL":16,"HAM":5,"BOR":17,"SAI":9,"HAD":6,"RUS":10,"PIA":4,"BEA":15}},{"lap":59,"positions":{"VER":1,"GAS":20,"ANT":12,"ALO":19,"LEC":3,"STR":14,"TSU":13,"ALB":11,"HUL":18,"LAW":8,"OCO":7,"NOR":2,"COL":16,"HAM":5,"BOR":17,"SAI":9,"HAD":6,"RUS":10,"PIA":4,"BEA":15}},{"lap":60,"positions":{"VER":1,"GAS":20,"ANT":12,"ALO":19,"LEC":3,"STR":14,"TSU":13,"ALB":11,"HUL":18,"LAW":8,"OCO":7,"NOR":2,"COL":16,"HAM":5,"BOR":17,"SAI":9,"HAD":6,"RUS":10,"PIA":4,"BEA":15}},{"lap":61,"positions":{"VER":1,"GAS":20,"ANT":12,"ALO":19,"LEC":3,"STR":14,"TSU":13,"ALB":11,"HUL":18,"LAW":8,"OCO":7,"NOR":2,"COL":16,"HAM":5,"BOR":17,"SAI":9,"HAD":6,"RUS":10,"PIA":4,"BEA":15}},{"lap":62,"positions":{"VER":1,"GAS":20,"ANT":12,"ALO":19,"LEC":3,"STR":14,"TSU":13,"ALB":10,"HUL":18,"LAW":8,"OCO":7,"NOR":2,"COL":16,"HAM":5,"BOR":17,"SAI":9,"HAD":6,"RUS":11,"PIA":4,"BEA":15}},{"lap":63,"positions":{"VER":1,"GAS":20,"ANT":12,"ALO":19,"LEC":3,"STR":14,"TSU":13,"ALB":10,"HUL":18,"LAW":8,"OCO":7,"NOR":2,"COL":16,"HAM":5,"BOR":17,"SAI":9,"HAD":6,"RUS":11,"PIA":4,"BEA":15}},{"lap":64,"positions":{"VER":1,"GAS":20,"ANT":12,"ALO":19,"LEC":3,"STR":18,"TSU":13,"ALB":9,"HUL":17,"LAW":8,"OCO":7,"NOR":2,"COL":15,"HAM":5,"BOR":16,"SAI":10,"HAD":6,"RUS":11,"PIA":4,"BEA":14}},{"lap":65,"positions":{"VER":1,"GAS":20,"ANT":12,"ALO":19,"LEC":3,"STR":18,"TSU":13,"ALB":9,"HUL":17,"LAW":8,"OCO":7,"NOR":2,"COL":15,"HAM":5,"BOR":16,"SAI":10,"HAD":6,"RUS":11,"PIA":4,"BEA":14}},{"lap":66,"positions":{"VER":1,"GAS":20,"ANT":12,"ALO":19,"LEC":3,"STR":18,"TSU":13,"ALB":9,"HUL":17,"LAW":8,"OCO":7,"NOR":2,"COL":15,"HAM":5,"BOR":16,"SAI":10,"HAD":6,"RUS":11,"PIA":4,"BEA":14}},{"lap":67,"positions":{"VER":1,"GAS":20,"ANT":12,"ALO":19,"LEC":3,"STR":18,"TSU":13,"ALB":9,"HUL":17,"LAW":8,"OCO":7,"NOR":2,"COL":15,"HAM":5,"BOR":16,"SAI":10,"HAD":6,"RUS":11,"PIA":4,"BEA":14}},{"lap":68,"positions":{"VER":1,"GAS":20,"ANT":12,"ALO":19,"LEC":3,"STR":18,"TSU":13,"ALB":9,"HUL":17,"LAW":8,"OCO":7,"NOR":2,"COL":15,"HAM":5,"BOR":16,"SAI":10,"HAD":6,"RUS":11,"PIA":4,"BEA":14}},{"lap":69,"positions":{"VER":1,"GAS":20,"ANT":18,"ALO":19,"LEC":3,"STR":17,"TSU":12,"ALB":9,"HUL":16,"LAW":8,"OCO":7,"NOR":2,"COL":14,"HAM":5,"BOR":15,"SAI":10,"HAD":6,"RUS":11,"PIA":4,"BEA":13}},{"lap":70,"positions":{"VER":1,"GAS":20,"ANT":18,"ALO":19,"LEC":3,"STR":17,"TSU":12,"ALB":9,"HUL":16,"LAW":8,"OCO":7,"NOR":2,"COL":14,"HAM":5,"BOR":15,"SAI":10,"HAD":6,"RUS":11,"PIA":4,"BEA":13}},{"lap":71,"positions":{"VER":1,"GAS":20,"ANT":18,"ALO":19,"LEC":3,"STR":17,"TSU":12,"ALB":9,"HUL":16,"LAW":8,"OCO":7,"NOR":2,"COL":14,"HAM":5,"BOR":15,"SAI":10,"HAD":6,"RUS":11,"PIA":4,"BEA":13}},{"lap":72,"positions":{"VER":1,"GAS":20,"ANT":18,"ALO":19,"LEC":3,"STR":17,"TSU":12,"ALB":9,"HUL":16,"LAW":8,"OCO":7,"NOR":2,"COL":14,"HAM":5,"BOR":15,"SAI":10,"HAD":6,"RUS":11,"PIA":4,"BEA":13}},{"lap":73,"positions":{"VER":1,"GAS":20,"ANT":18,"ALO":19,"LEC":3,"STR":16,"TSU":17,"ALB":9,"HUL":15,"LAW":8,"OCO":7,"NOR":2,"COL":13,"HAM":5,"BOR":14,"SAI":10,"HAD":6,"RUS":11,"PIA":4,"BEA":12}},{"lap":74,"positions":{"VER":1,"GAS":20,"ANT":18,"ALO":19,"LEC":3,"STR":16,"TSU":17,"ALB":9,"HUL":15,"LAW":8,"OCO":7,"NOR":2,"COL":13,"HAM":5,"BOR":14,"SAI":10,"HAD":6,"RUS":11,"PIA":4,"BEA":12}},{"lap":75,"positions":{"VER":1,"GAS":20,"ANT":18,"ALO":19,"LEC":3,"STR":16,"TSU":17,"ALB":9,"HUL":15,"LAW":8,"OCO":7,"NOR":2,"COL":13,"HAM":5,"BOR":14,"SAI":10,"HAD":6,"RUS":11,"PIA":4,"BEA":12}},{"lap":76,"positions":{"VER":1,"GAS":20,"ANT":18,"ALO":19,"LEC":3,"STR":15,"TSU":17,"ALB":9,"HUL":16,"LAW":8,"OCO":7,"NOR":2,"COL":13,"HAM":5,"BOR":14,"SAI":10,"HAD":6,"RUS":11,"PIA":4,"BEA":12}},{"lap":77,"positions":{"VER":4,"GAS":20,"ANT":18,"ALO":19,"LEC":2,"STR":15,"TSU":17,"ALB":9,"HUL":16,"LAW":8,"OCO":7,"NOR":1,"COL":13,"HAM":5,"BOR":14,"SAI":10,"HAD":6,"RUS":11,"PIA":3,"BEA":12}},{"lap":78,"positions":{"VER":4,"GAS":20,"ANT":18,"ALO":19,"LEC":2,"STR":15,"TSU":17,"ALB":9,"HUL":16,"LAW":8,"OCO":7,"NOR":1,"COL":13,"HAM":5,"BOR":14,"SAI":10,"HAD":6,"RUS":11,"PIA":3,"BEA":12}}],"dnfLaps":{"GAS":8,"ALO":36},"stints":{"VER":[{"startLap":1,"endLap":28,"compound":"HARD"},{"startLap":29,"endLap":77,"compound":"MEDIUM"},{"startLap":78,"endLap":78,"compound":"SOFT"}],"GAS":[{"startLap":1,"endLap":8,"compound":"MEDIUM"}],"ANT":[{"startLap":1,"endLap":69,"compound":"HARD"},{"startLap":70,"endLap":71,"compound":"MEDIUM"},{"startLap":72,"endLap":75,"compound":"HARD"}],"ALO":[{"startLap":1,"endLap":36,"compound":"HARD"}],"LEC":[{"startLap":1,"endLap":22,"compound":"MEDIUM"},{"startLap":23,"endLap":49,"compound":"HARD"},{"startLap":50,"endLap":78,"compound":"MEDIUM"}],"STR":[{"startLap":1,"endLap":64,"compound":"HARD"},{"startLap":65,"endLap":76,"compound":"MEDIUM"}],"TSU":[{"startLap":1,"endLap":1,"compound":"SOFT"},{"startLap":2,"endLap":73,"compound":"HARD"},{"startLap":74,"endLap":76,"compound":"MEDIUM"}],"ALB":[{"startLap":1,"endLap":40,"compound":"MEDIUM"},{"startLap":41,"endLap":76,"compound":"HARD"}],"HUL":[{"startLap":1,"endLap":12,"compound":"MEDIUM"},{"startLap":13,"endLap":44,"compound":"HARD"},{"startLap":45,"endLap":76,"compound":"SOFT"}],"LAW":[{"startLap":1,"endLap":31,"compound":"MEDIUM"},{"startLap":32,"endLap":40,"compound":"SOFT"},{"startLap":41,"endLap":77,"compound":"HARD"}],"OCO":[{"startLap":1,"endLap":28,"compound":"MEDIUM"},{"startLap":29,"endLap":77,"compound":"HARD"}],"NOR":[{"startLap":1,"endLap":19,"compound":"MEDIUM"},{"startLap":20,"endLap":78,"compound":"HARD"}],"COL":[{"startLap":1,"endLap":13,"compound":"HARD"},{"startLap":14,"endLap":76,"compound":"MEDIUM"}],"HAM":[{"startLap":1,"endLap":56,"compound":"HARD"},{"startLap":57,"endLap":78,"compound":"MEDIUM"}],"BOR":[{"startLap":1,"endLap":1,"compound":"MEDIUM"},{"startLap":2,"endLap":26,"compound":"HARD"},{"startLap":27,"endLap":35,"compound":"SOFT"},{"startLap":36,"endLap":76,"compound":"MEDIUM"}],"SAI":[{"startLap":1,"endLap":48,"compound":"HARD"},{"startLap":49,"endLap":76,"compound":"MEDIUM"}],"HAD":[{"startLap":1,"endLap":14,"compound":"MEDIUM"},{"startLap":15,"endLap":19,"compound":"SOFT"},{"startLap":20,"endLap":77,"compound":"HARD"}],"RUS":[{"startLap":1,"endLap":53,"compound":"HARD"},{"startLap":54,"endLap":68,"compound":"MEDIUM"},{"startLap":69,"endLap":76,"compound":"HARD"}],"PIA":[{"startLap":1,"endLap":20,"compound":"MEDIUM"},{"startLap":21,"endLap":78,"compound":"HARD"}],"BEA":[{"startLap":1,"endLap":1,"compound":"MEDIUM"},{"startLap":2,"endLap":17,"compound":"HARD"},{"startLap":18,"endLap":76,"compound":"MEDIUM"}]},"safetyCars":[{"startLap":1,"endLap":4,"type":"VSC"}],"gapsByLap":[{"lap":1,"gaps":{"VER":3.68,"GAS":28.883,"ANT":11.381,"ALO":4.992,"LEC":1.141,"STR":14.678,"TSU":27.136,"ALB":8.139,"HUL":9.448,"LAW":7.183,"OCO":6.586,"NOR":0.0,"COL":13.237,"HAM":6.066,"BOR":62.224,"SAI":9.073,"HAD":4.227,"RUS":10.737,"PIA":2.801,"BEA":56.592}},{"lap":2,"gaps":{"VER":5.364,"GAS":33.223,"ANT":18.155,"ALO":7.43,"LEC":1.276,"STR":19.85,"TSU":31.378,"ALB":15.657,"HUL":17.218,"LAW":14.857,"OCO":13.479,"NOR":0.0,"COL":19.497,"HAM":12.869,"BOR":67.336,"SAI":16.048,"HAD":6.285,"RUS":17.696,"PIA":4.633,"BEA":62.612}},{"lap":3,"gaps":{"VER":5.164,"GAS":32.931,"ANT":18.011,"ALO":7.626,"LEC":1.066,"STR":20.188,"TSU":30.908,"ALB":14.988,"HUL":16.309,"LAW":14.346,"OCO":13.651,"NOR":0.0,"COL":19.395,"HAM":13.066,"BOR":67.683,"SAI":15.419,"HAD":6.684,"RUS":17.244,"PIA":3.794,"BEA":63.931}},{"lap":4,"gaps":{"VER":3.89,"GAS":22.876,"ANT":13.022,"ALO":5.737,"LEC":0.75,"STR":14.977,"TSU":22.441,"ALB":9.43,"HUL":11.441,"LAW":8.136,"OCO":7.317,"NOR":0.0,"COL":14.307,"HAM":6.232,"BOR":49.728,"SAI":10.663,"HAD":4.76,"RUS":12.347,"PIA":2.906,"BEA":44.494}},{"lap":5,"gaps":{"VER":6.64,"GAS":23.69,"ANT":15.349,"ALO":8.627,"LEC":1.501,"STR":17.212,"TSU":23.054,"ALB":11.845,"HUL":13.866,"LAW":10.852,"OCO":9.933,"NOR":0.0,"COL":16.256,"HAM":9.239,"BOR":48.072,"SAI":13.193,"HAD":7.662,"RUS":14.873,"PIA":4.904,"BEA":42.02}},{"lap":6,"gaps":{"VER":7.479,"GAS":22.572,"ANT":16.934,"ALO":9.879,"LEC":1.596,"STR":18.346,"TSU":22.163,"ALB":14.099,"HUL":15.668,"LAW":13.222,"OCO":11.267,"NOR":0.0,"COL":17.83,"HAM":10.292,"BOR":44.657,"SAI":15.077,"HAD":8.633,"RUS":16.451,"PIA":5.525,"BEA":37.703}},{"lap":7,"gaps":{"VER":7.977,"GAS":23.364,"ANT":19.658,"ALO":11.631,"LEC":1.782,"STR":21.072,"TSU":22.85,"ALB":16.916,"HUL":18.462,"LAW":16.259,"OCO":13.342,"NOR":0.0,"COL":20.275,"HAM":12.753,"BOR":41.908,"SAI":18.184,"HAD":9.717,"RUS":19.195,"PIA":6.316,"BEA":34.291}},{"lap":8,"gaps":{"VER":8.065,"GAS":38.98,"ANT":22.909,"ALO":13.11,"LEC":2.146,"STR":25.109,"TSU":28.575,"ALB":19.761,"HUL":21.136,"LAW":18.984,"OCO":14.923,"NOR":0.0,"COL":23.636,"HAM":14.166,"BOR":42.613,"SAI":20.942,"HAD":10.479,"RUS":22.362,"PIA":6.719,"BEA":34.968}},{"lap":9,"gaps":{"VER":7.122,"ANT":24.087,"ALO":13.145,"LEC":1.21,"STR":25.282,"TSU":26.038,"ALB":21.764,"HUL":23.019,"LAW":21.386,"OCO":15.487,"NOR":0.0,"COL":24.685,"HAM":14.036,"BOR":38.876,"SAI":22.467,"HAD":10.299,"RUS":23.604,"PIA":6.852,"BEA":29.287}},{"lap":10,"gaps":{"VER":5.906,"ANT":25.225,"ALO":12.927,"LEC":0.737,"STR":26.605,"TSU":27.476,"ALB":22.907,"HUL":24.141,"LAW":22.422,"OCO":15.432,"NOR":0.0,"COL":26.009,"HAM":14.179,"BOR":35.273,"SAI":23.75,"HAD":8.443,"RUS":24.72,"PIA":5.627,"BEA":28.457}},{"lap":11,"gaps":{"VER":3.616,"ANT":25.348,"ALO":10.625,"LEC":0.856,"STR":26.952,"TSU":27.793,"ALB":22.583,"HUL":23.774,"LAW":21.999,"OCO":12.98,"NOR":0.0,"COL":26.089,"HAM":11.528,"BOR":31.758,"SAI":23.409,"HAD":6.855,"RUS":24.802,"PIA":3.191,"BEA":28.703}},{"lap":12,"gaps":{"VER":5.444,"ANT":28.836,"ALO":11.644,"LEC":0.995,"STR":30.217,"TSU":31.13,"ALB":25.943,"HUL":44.217,"LAW":25.47,"OCO":14.038,"NOR":0.0,"COL":29.616,"HAM":12.758,"BOR":33.262,"SAI":27.243,"HAD":7.931,"RUS":28.228,"PIA":4.284,"BEA":31.804}},{"lap":13,"gaps":{"VER":6.578,"ANT":31.716,"ALO":12.067,"LEC":1.214,"STR":33.616,"TSU":34.443,"ALB":29.199,"HUL":46.508,"LAW":28.873,"OCO":15.291,"NOR":0.0,"COL":49.545,"HAM":13.569,"BOR":36.362,"SAI":30.404,"HAD":9.031,"RUS":31.141,"PIA":5.044,"BEA":35.496}},{"lap":14,"gaps":{"VER":7.266,"ANT":34.669,"ALO":12.24,"LEC":1.722,"STR":35.966,"TSU":37.096,"ALB":32.894,"HUL":46.492,"LAW":32.323,"OCO":15.622,"NOR":0.0,"COL":53.485,"HAM":13.598,"BOR":38.721,"SAI":33.711,"HAD":26.981,"RUS":34.266,"PIA":5.334,"BEA":37.76}},{"lap":15,"gaps":{"VER":7.973,"ANT":38.854,"ALO":12.16,"LEC":2.091,"STR":39.64,"TSU":40.509,"ALB":37.364,"HUL":47.372,"LAW":36.811,"OCO":16.526,"NOR":0.0,"COL":53.321,"HAM":13.916,"BOR":41.695,"SAI":38.037,"HAD":31.079,"RUS":38.357,"PIA":5.183,"BEA":41.281}},{"lap":16,"gaps":{"VER":8.451,"ANT":44.685,"ALO":31.414,"LEC":2.92,"STR":45.172,"TSU":46.039,"ALB":43.142,"HUL":50.775,"LAW":42.589,"OCO":36.552,"NOR":0.0,"COL":53.842,"HAM":14.943,"BOR":47.159,"SAI":43.82,"HAD":32.146,"RUS":44.209,"PIA":5.912,"BEA":47.005}},{"lap":17,"gaps":{"VER":8.923,"ANT":51.208,"ALO":37.038,"LEC":3.529,"STR":68.338,"TSU":52.461,"ALB":49.461,"HUL":56.085,"LAW":48.909,"OCO":40.694,"NOR":0.0,"COL":56.73,"HAM":15.261,"BOR":53.437,"SAI":50.221,"HAD":34.678,"RUS":50.607,"PIA":6.71,"BEA":70.212}},{"lap":18,"gaps":{"VER":8.678,"ANT":56.064,"ALO":38.598,"LEC":3.07,"STR":72.621,"TSU":56.789,"ALB":54.416,"HUL":58.849,"LAW":53.854,"OCO":41.188,"NOR":0.0,"COL":59.801,"HAM":31.843,"BOR":57.379,"SAI":55.084,"HAD":35.77,"RUS":55.453,"PIA":6.364,"BEA":73.358}},{"lap":19,"gaps":{"VER":5.505,"ANT":57.102,"ALO":37.238,"LEC":0.0,"STR":70.616,"TSU":57.955,"ALB":55.109,"HUL":59.321,"LAW":54.601,"OCO":39.342,"NOR":13.668,"COL":60.066,"HAM":31.299,"BOR":58.522,"SAI":56.02,"HAD":50.508,"RUS":56.496,"PIA":2.827,"BEA":71.057}},{"lap":20,"gaps":{"VER":5.931,"ANT":61.137,"ALO":39.698,"LEC":0.0,"STR":72.242,"TSU":62.044,"ALB":58.23,"HUL":63.895,"LAW":57.192,"OCO":41.134,"NOR":16.894,"COL":64.555,"HAM":31.557,"BOR":63.05,"SAI":59.068,"HAD":54.876,"RUS":60.202,"PIA":21.74,"BEA":72.78}},{"lap":21,"gaps":{"VER":5.397,"ANT":63.269,"ALO":41.837,"LEC":0.0,"STR":73.367,"TSU":64.147,"ALB":59.544,"HUL":66.263,"LAW":58.467,"OCO":42.855,"NOR":16.371,"COL":66.987,"HAM":31.525,"BOR":64.986,"SAI":60.747,"HAD":55.23,"RUS":62.195,"PIA":23.972,"BEA":74.187}},{"lap":22,"gaps":{"VER":0.0,"ANT":59.854,"ALO":40.087,"LEC":11.724,"STR":69.352,"TSU":60.854,"ALB":55.857,"HUL":63.084,"LAW":54.513,"OCO":40.667,"NOR":10.529,"COL":64.107,"HAM":25.84,"BOR":61.962,"SAI":57.123,"HAD":50.899,"RUS":58.808,"PIA":17.102,"BEA":70.061}},{"lap":23,"gaps":{"VER":0.0,"ANT":61.573,"ALO":42.78,"LEC":16.569,"STR":70.677,"TSU":62.533,"ALB":57.159,"HUL":65.387,"LAW":56.043,"OCO":43.488,"NOR":10.59,"COL":66.479,"HAM":25.598,"BOR":63.924,"SAI":58.619,"HAD":53.226,"RUS":60.454,"PIA":19.638,"BEA":71.349}},{"lap":24,"gaps":{"VER":0.0,"ANT":63.331,"ALO":45.347,"LEC":17.408,"STR":72.538,"TSU":64.378,"ALB":58.932,"HUL":67.261,"LAW":57.574,"OCO":46.218,"NOR":10.629,"COL":68.531,"HAM":25.629,"BOR":66.029,"SAI":60.456,"HAD":55.835,"RUS":62.208,"PIA":19.944,"BEA":73.224}},{"lap":25,"gaps":{"VER":0.0,"ANT":66.933,"ALO":47.857,"LEC":16.851,"STR":74.604,"TSU":67.616,"ALB":61.41,"HUL":69.624,"LAW":59.989,"OCO":48.763,"NOR":9.854,"COL":70.565,"HAM":25.152,"BOR":68.819,"SAI":66.007,"HAD":58.492,"RUS":66.249,"PIA":19.709,"BEA":76.418}},{"lap":26,"gaps":{"VER":0.0,"ANT":70.124,"ALO":47.862,"LEC":15.277,"STR":77.217,"TSU":70.858,"ALB":62.386,"HUL":72.06,"LAW":61.157,"OCO":49.002,"NOR":8.293,"COL":89.849,"HAM":23.668,"BOR":88.706,"SAI":69.029,"HAD":59.829,"RUS":69.452,"PIA":18.381,"BEA":78.164}},{"lap":27,"gaps":{"VER":0.0,"ANT":73.247,"ALO":48.283,"LEC":13.773,"STR":77.921,"TSU":74.1,"ALB":63.248,"HUL":75.209,"LAW":61.874,"OCO":49.384,"NOR":6.592,"COL":93.763,"HAM":21.878,"BOR":92.592,"SAI":72.294,"HAD":59.988,"RUS":72.582,"PIA":16.83,"BEA":78.841}},{"lap":28,"gaps":{"VER":11.441,"ANT":71.947,"ALO":43.487,"LEC":7.412,"STR":73.983,"TSU":72.676,"ALB":58.739,"HUL":73.263,"LAW":57.566,"OCO":62.179,"NOR":0.0,"COL":90.688,"HAM":16.088,"BOR":87.402,"SAI":70.701,"HAD":55.219,"RUS":71.045,"PIA":11.176,"BEA":74.757}},{"lap":29,"gaps":{"VER":14.235,"ANT":75.244,"ALO":43.989,"LEC":5.84,"STR":78.325,"TSU":76.212,"ALB":59.931,"HUL":77.235,"LAW":58.529,"OCO":65.89,"NOR":0.0,"COL":90.825,"HAM":17.121,"BOR":86.818,"SAI":74.037,"HAD":55.939,"RUS":74.515,"PIA":10.135,"BEA":80.545}},{"lap":30,"gaps":{"VER":12.05,"ANT":78.391,"ALO":44.037,"LEC":3.712,"STR":81.312,"TSU":79.118,"ALB":59.56,"HUL":80.368,"LAW":57.877,"OCO":64.427,"NOR":0.0,"COL":88.864,"HAM":15.746,"BOR":85.102,"SAI":77.422,"HAD":55.112,"RUS":77.77,"PIA":7.744,"BEA":82.064}},{"lap":31,"gaps":{"VER":10.386,"ANT":81.403,"ALO":43.382,"LEC":3.688,"STR":84.236,"TSU":82.409,"ALB":59.633,"HUL":83.46,"LAW":74.611,"OCO":63.06,"NOR":0.0,"COL":88.074,"HAM":14.597,"BOR":86.519,"SAI":77.902,"HAD":54.604,"RUS":79.041,"PIA":6.682,"BEA":85.194}},{"lap":32,"gaps":{"VER":11.099,"ANT":86.381,"ALO":44.759,"LEC":5.395,"STR":90.023,"TSU":88.649,"ALB":77.916,"HUL":89.351,"LAW":79.101,"OCO":63.852,"NOR":0.0,"COL":93.208,"HAM":15.562,"BOR":91.155,"SAI":83.245,"HAD":56.2,"RUS":83.714,"PIA":8.793,"BEA":90.71}},{"lap":33,"gaps":{"VER":12.67,"ANT":91.083,"ALO":45.94,"LEC":6.268,"STR":93.611,"TSU":92.042,"ALB":85.51,"HUL":92.549,"LAW":82.744,"OCO":64.43,"NOR":0.0,"COL":97.094,"HAM":17.456,"BOR":95.789,"SAI":89.481,"HAD":57.602,"RUS":90.207,"PIA":10.476,"BEA":94.852}},{"lap":34,"gaps":{"VER":13.781,"ANT":95.157,"ALO":48.598,"LEC":6.559,"STR":99.121,"TSU":95.976,"ALB":91.053,"HUL":96.26,"LAW":84.48,"OCO":64.898,"NOR":0.0,"COL":101.109,"HAM":20.333,"BOR":100.376,"SAI":94.012,"HAD":58.983,"RUS":94.454,"PIA":11.734,"BEA":99.888}},{"lap":35,"gaps":{"VER":14.927,"ANT":100.431,"ALO":50.438,"LEC":6.724,"STR":103.154,"TSU":102.061,"ALB":93.25,"HUL":102.67,"LAW":86.238,"OCO":66.56,"NOR":0.0,"COL":105.595,"HAM":23.975,"BOR":121.439,"SAI":99.292,"HAD":61.011,"RUS":99.489,"PIA":12.369,"BEA":103.71}},{"lap":36,"gaps":{"VER":15.118,"ANT":105.515,"ALO":51.853,"LEC":5.994,"STR":107.281,"TSU":106.221,"ALB":94.65,"HUL":106.527,"LAW":91.724,"OCO":67.924,"NOR":0.0,"COL":108.765,"HAM":26.408,"BOR":125.261,"SAI":104.285,"HAD":62.351,"RUS":104.656,"PIA":12.691,"BEA":107.984}},{"lap":37,"gaps":{"VER":15.473,"ANT":109.715,"ALO":127.183,"LEC":5.429,"STR":111.557,"TSU":110.484,"ALB":96.133,"HUL":110.761,"LAW":92.944,"OCO":70.451,"NOR":0.0,"COL":112.755,"HAM":29.026,"BOR":125.475,"SAI":108.368,"HAD":64.1,"RUS":108.911,"PIA":13.417,"BEA":112.199}},{"lap":38,"gaps":{"VER":15.243,"ANT":113.189,"LEC":5.092,"STR":114.902,"TSU":113.745,"ALB":96.755,"HUL":114.126,"LAW":94.001,"OCO":71.842,"NOR":0.0,"COL":116.576,"HAM":30.057,"BOR":125.538,"SAI":111.987,"HAD":65.593,"RUS":112.472,"PIA":12.985,"BEA":115.625}},{"lap":39,"gaps":{"VER":15.887,"ANT":117.769,"LEC":5.091,"STR":119.566,"TSU":118.483,"ALB":97.917,"HUL":118.861,"LAW":95.66,"OCO":76.111,"NOR":0.0,"COL":121.324,"HAM":31.362,"BOR":127.285,"SAI":116.665,"HAD":68.372,"RUS":117.196,"PIA":13.438,"BEA":120.275}},{"lap":40,"gaps":{"VER":15.071,"ANT":121.482,"LEC":3.91,"STR":123.114,"TSU":122.159,"ALB":114.836,"HUL":122.428,"LAW":112.89,"OCO":77.399,"NOR":0.0,"COL":124.53,"HAM":31.076,"BOR":128.383,"SAI":120.416,"HAD":70.16,"RUS":120.895,"PIA":12.545,"BEA":123.806}},{"lap":41,"gaps":{"VER":15.435,"ANT":125.516,"LEC":4.719,"STR":127.789,"TSU":126.405,"ALB":122.208,"HUL":126.977,"LAW":119.747,"OCO":81.499,"NOR":0.0,"COL":129.37,"HAM":32.161,"BOR":131.204,"SAI":123.212,"HAD":73.376,"RUS":124.141,"PIA":12.816,"BEA":128.521}},{"lap":42,"gaps":{"VER":15.472,"ANT":128.217,"LEC":5.433,"STR":130.733,"TSU":129.278,"ALB":126.608,"HUL":129.873,"LAW":122.071,"OCO":83.32,"NOR":0.0,"COL":132.749,"HAM":32.726,"BOR":134.463,"SAI":125.499,"HAD":78.642,"RUS":127.339,"PIA":12.534,"BEA":131.526}},{"lap":43,"gaps":{"VER":15.865,"ANT":132.353,"LEC":5.815,"STR":134.321,"TSU":133.154,"ALB":131.072,"HUL":133.628,"LAW":123.828,"OCO":85.73,"NOR":0.0,"COL":136.116,"HAM":33.406,"BOR":137.326,"SAI":127.206,"HAD":83.392,"RUS":131.659,"PIA":13.541,"BEA":135.0}},{"lap":44,"gaps":{"VER":16.373,"ANT":137.366,"LEC":6.208,"STR":139.064,"TSU":138.109,"ALB":136.425,"HUL":155.383,"LAW":125.914,"OCO":89.182,"NOR":0.0,"COL":140.683,"HAM":34.22,"BOR":141.804,"SAI":129.393,"HAD":86.45,"RUS":136.859,"PIA":14.345,"BEA":139.639}},{"lap":45,"gaps":{"VER":16.219,"ANT":142.233,"LEC":6.034,"STR":143.725,"TSU":142.991,"ALB":141.265,"HUL":160.067,"LAW":127.135,"OCO":93.25,"NOR":0.0,"COL":145.009,"HAM":34.685,"BOR":145.878,"SAI":131.133,"HAD":89.98,"RUS":141.667,"PIA":15.085,"BEA":144.312}},{"lap":46,"gaps":{"VER":16.939,"ANT":147.321,"LEC":6.196,"STR":148.568,"TSU":148.06,"ALB":146.42,"HUL":161.799,"LAW":128.434,"OCO":96.08,"NOR":0.0,"COL":151.022,"HAM":35.831,"BOR":151.554,"SAI":133.037,"HAD":95.41,"RUS":146.779,"PIA":15.783,"BEA":149.429}},{"lap":47,"gaps":{"VER":17.441,"ANT":153.095,"LEC":6.373,"STR":154.595,"TSU":153.906,"ALB":151.236,"HUL":162.665,"LAW":129.538,"OCO":99.064,"NOR":0.0,"COL":156.554,"HAM":37.177,"BOR":157.324,"SAI":134.196,"HAD":98.182,"RUS":152.381,"PIA":15.518,"BEA":155.15}},{"lap":48,"gaps":{"VER":16.278,"ANT":156.238,"LEC":5.403,"STR":157.512,"TSU":157.184,"ALB":155.728,"HUL":163.21,"LAW":129.255,"OCO":101.431,"NOR":0.0,"COL":159.093,"HAM":36.589,"BOR":159.639,"SAI":151.37,"HAD":99.932,"RUS":154.157,"PIA":30.845,"BEA":158.414}},{"lap":49,"gaps":{"VER":13.855,"ANT":157.882,"LEC":20.696,"STR":159.079,"TSU":158.498,"ALB":157.278,"HUL":165.202,"LAW":128.138,"OCO":102.982,"NOR":0.0,"COL":160.568,"HAM":35.474,"BOR":161.366,"SAI":153.648,"HAD":101.324,"RUS":154.852,"PIA":32.622,"BEA":159.651}},{"lap":50,"gaps":{"VER":0.0,"ANT":148.694,"LEC":9.515,"STR":149.799,"TSU":149.422,"ALB":148.163,"HUL":153.346,"LAW":115.336,"OCO":92.603,"NOR":2.612,"COL":152.252,"HAM":22.887,"BOR":152.764,"SAI":140.654,"HAD":90.278,"RUS":142.537,"PIA":18.462,"BEA":150.473}},{"lap":51,"gaps":{"VER":0.0,"ANT":153.87,"LEC":8.718,"STR":154.923,"TSU":154.524,"ALB":152.826,"HUL":159.358,"LAW":115.57,"OCO":95.862,"NOR":5.684,"COL":157.809,"HAM":23.281,"BOR":158.297,"SAI":139.985,"HAD":94.045,"RUS":143.467,"PIA":18.01,"BEA":157.513}},{"lap":52,"gaps":{"VER":0.0,"ANT":159.504,"LEC":6.811,"STR":160.85,"TSU":160.087,"ALB":156.628,"HUL":163.406,"LAW":114.619,"OCO":96.984,"NOR":4.395,"COL":161.904,"HAM":22.447,"BOR":162.778,"SAI":138.291,"HAD":95.435,"RUS":143.162,"PIA":15.769,"BEA":161.173}},{"lap":53,"gaps":{"VER":0.0,"ANT":161.22,"LEC":4.671,"STR":162.266,"TSU":161.935,"ALB":158.484,"HUL":165.487,"LAW":112.428,"OCO":98.57,"NOR":2.696,"COL":164.612,"HAM":21.085,"BOR":165.196,"SAI":152.19,"HAD":95.308,"RUS":153.548,"PIA":12.226,"BEA":163.932}},{"lap":54,"gaps":{"VER":0.0,"ANT":164.951,"LEC":5.907,"STR":166.187,"TSU":165.629,"ALB":160.001,"HUL":168.456,"LAW":111.877,"OCO":100.442,"NOR":3.132,"COL":167.45,"HAM":21.43,"BOR":168.028,"SAI":157.019,"HAD":99.159,"RUS":158.458,"PIA":11.057,"BEA":166.88}},{"lap":55,"gaps":{"VER":0.0,"ANT":168.297,"LEC":4.784,"STR":169.372,"TSU":168.82,"ALB":161.467,"HUL":171.991,"LAW":111.854,"OCO":103.314,"NOR":2.505,"COL":170.522,"HAM":22.467,"BOR":171.231,"SAI":156.798,"HAD":101.402,"RUS":159.293,"PIA":11.681,"BEA":169.919}},{"lap":56,"gaps":{"VER":0.0,"ANT":171.263,"LEC":3.796,"STR":172.407,"TSU":171.898,"ALB":165.296,"HUL":174.637,"LAW":113.484,"OCO":105.525,"NOR":1.996,"COL":173.681,"HAM":40.703,"BOR":174.352,"SAI":156.064,"HAD":103.556,"RUS":162.442,"PIA":11.464,"BEA":172.895}},{"lap":57,"gaps":{"VER":0.0,"ANT":174.356,"LEC":2.82,"STR":175.483,"TSU":174.977,"ALB":166.014,"HUL":177.88,"LAW":114.649,"OCO":107.978,"NOR":1.254,"COL":176.689,"HAM":46.753,"BOR":177.372,"SAI":155.67,"HAD":105.406,"RUS":163.739,"PIA":10.856,"BEA":176.061}},{"lap":58,"gaps":{"VER":0.0,"ANT":177.502,"LEC":2.139,"STR":178.352,"TSU":177.983,"ALB":166.562,"HUL":180.575,"LAW":117.086,"OCO":109.915,"NOR":1.166,"COL":179.691,"HAM":49.855,"BOR":180.243,"SAI":156.637,"HAD":107.143,"RUS":164.529,"PIA":10.439,"BEA":178.852}},{"lap":59,"gaps":{"VER":0.0,"ANT":181.208,"LEC":1.496,"STR":182.185,"TSU":181.661,"ALB":166.721,"HUL":184.512,"LAW":118.508,"OCO":111.702,"NOR":0.923,"COL":183.404,"HAM":51.191,"BOR":183.89,"SAI":159.241,"HAD":109.51,"RUS":165.261,"PIA":9.005,"BEA":182.735}},{"lap":60,"gaps":{"VER":0.0,"ANT":184.817,"LEC":1.849,"STR":185.677,"TSU":185.383,"ALB":167.359,"HUL":187.932,"LAW":120.092,"OCO":114.22,"NOR":1.419,"COL":187.003,"HAM":51.87,"BOR":187.61,"SAI":160.846,"HAD":112.43,"RUS":166.38,"PIA":7.662,"BEA":186.316}},{"lap":61,"gaps":{"VER":0.0,"ANT":188.343,"LEC":2.19,"STR":189.364,"TSU":188.866,"ALB":168.341,"HUL":191.909,"LAW":121.201,"OCO":116.8,"NOR":1.554,"COL":190.817,"HAM":52.237,"BOR":191.343,"SAI":162.404,"HAD":115.435,"RUS":167.314,"PIA":7.083,"BEA":189.967}},{"lap":62,"gaps":{"VER":0.0,"ANT":191.661,"LEC":2.706,"STR":192.516,"TSU":192.166,"ALB":169.581,"HUL":198.344,"LAW":122.935,"OCO":119.34,"NOR":1.938,"COL":193.901,"HAM":52.023,"BOR":194.479,"SAI":164.264,"HAD":118.181,"RUS":186.262,"PIA":7.166,"BEA":193.201}},{"lap":63,"gaps":{"VER":0.0,"ANT":195.457,"LEC":2.983,"STR":196.402,"TSU":196.001,"ALB":169.575,"HUL":202.462,"LAW":125.458,"OCO":122.547,"NOR":2.151,"COL":197.69,"HAM":51.128,"BOR":198.297,"SAI":167.04,"HAD":121.164,"RUS":188.935,"PIA":6.459,"BEA":196.949}},{"lap":64,"gaps":{"VER":0.0,"ANT":198.674,"LEC":3.012,"STR":218.339,"TSU":199.273,"ALB":170.563,"HUL":207.369,"LAW":127.373,"OCO":125.21,"NOR":2.224,"COL":200.829,"HAM":52.194,"BOR":205.215,"SAI":172.006,"HAD":124.223,"RUS":187.559,"PIA":6.423,"BEA":200.113}},{"lap":65,"gaps":{"VER":0.0,"ANT":201.248,"LEC":3.285,"STR":221.161,"TSU":201.762,"ALB":170.597,"HUL":209.818,"LAW":131.41,"OCO":128.359,"NOR":2.58,"COL":203.045,"HAM":53.31,"BOR":209.053,"SAI":173.038,"HAD":127.226,"RUS":186.717,"PIA":5.962,"BEA":202.168}},{"lap":66,"gaps":{"VER":0.0,"ANT":203.432,"LEC":2.986,"STR":220.833,"TSU":204.158,"ALB":170.253,"HUL":211.538,"LAW":133.151,"OCO":131.955,"NOR":2.334,"COL":205.348,"HAM":54.755,"BOR":211.163,"SAI":172.088,"HAD":129.532,"RUS":185.421,"PIA":5.854,"BEA":204.702}},{"lap":67,"gaps":{"VER":0.0,"ANT":203.432,"LEC":2.36,"STR":220.159,"TSU":204.576,"ALB":169.63,"HUL":213.432,"LAW":135.009,"OCO":133.805,"NOR":1.79,"COL":207.815,"HAM":55.22,"BOR":213.024,"SAI":173.538,"HAD":132.998,"RUS":183.353,"PIA":5.317,"BEA":205.513}},{"lap":68,"gaps":{"VER":0.0,"ANT":202.178,"LEC":1.723,"STR":219.212,"TSU":204.269,"ALB":168.242,"HUL":214.876,"LAW":136.099,"OCO":134.999,"NOR":1.132,"COL":208.642,"HAM":54.808,"BOR":213.999,"SAI":171.253,"HAD":134.005,"RUS":198.157,"PIA":4.304,"BEA":206.842}},{"lap":69,"gaps":{"VER":0.0,"ANT":220.236,"LEC":1.764,"STR":218.396,"TSU":206.538,"ALB":168.969,"HUL":215.787,"LAW":137.172,"OCO":135.921,"NOR":1.053,"COL":209.282,"HAM":54.33,"BOR":214.921,"SAI":171.966,"HAD":134.859,"RUS":200.213,"PIA":3.879,"BEA":206.966}},{"lap":70,"gaps":{"VER":0.0,"ANT":223.927,"LEC":2.002,"STR":218.799,"TSU":206.772,"ALB":169.167,"HUL":216.716,"LAW":138.265,"OCO":137.178,"NOR":1.479,"COL":210.177,"HAM":53.775,"BOR":216.205,"SAI":170.514,"HAD":136.049,"RUS":198.704,"PIA":3.966,"BEA":207.817}},{"lap":71,"gaps":{"VER":0.0,"ANT":239.381,"LEC":2.254,"STR":219.296,"TSU":206.321,"ALB":168.86,"HUL":217.26,"LAW":139.26,"OCO":137.948,"NOR":1.783,"COL":210.375,"HAM":52.805,"BOR":216.631,"SAI":170.876,"HAD":136.789,"RUS":196.699,"PIA":3.503,"BEA":207.507}},{"lap":72,"gaps":{"VER":0.0,"ANT":242.318,"LEC":2.661,"STR":219.385,"TSU":205.569,"ALB":168.658,"HUL":217.87,"LAW":139.58,"OCO":138.644,"NOR":2.091,"COL":210.438,"HAM":51.006,"BOR":217.183,"SAI":170.598,"HAD":137.637,"RUS":194.492,"PIA":3.572,"BEA":206.862}},{"lap":73,"gaps":{"VER":0.0,"ANT":239.748,"LEC":2.789,"STR":219.116,"TSU":221.274,"ALB":167.587,"HUL":218.366,"LAW":139.956,"OCO":139.075,"NOR":2.225,"COL":209.886,"HAM":48.875,"BOR":217.736,"SAI":170.907,"HAD":138.14,"RUS":191.867,"PIA":3.565,"BEA":205.996}},{"lap":74,"gaps":{"VER":0.0,"ANT":236.917,"LEC":2.688,"STR":219.828,"TSU":224.392,"ALB":165.835,"HUL":219.428,"LAW":140.673,"OCO":139.306,"NOR":2.163,"COL":209.101,"HAM":47.914,"BOR":218.218,"SAI":168.853,"HAD":138.418,"RUS":188.923,"PIA":3.409,"BEA":205.012}},{"lap":75,"gaps":{"VER":0.0,"ANT":235.407,"LEC":2.687,"STR":219.797,"TSU":222.961,"ALB":164.091,"HUL":219.588,"LAW":141.086,"OCO":139.676,"NOR":2.224,"COL":208.677,"HAM":47.887,"BOR":218.555,"SAI":167.048,"HAD":138.649,"RUS":186.352,"PIA":3.204,"BEA":204.467}},{"lap":76,"gaps":{"VER":0.0,"LEC":2.182,"STR":220.925,"TSU":222.379,"ALB":162.399,"HUL":222.074,"LAW":140.646,"OCO":139.812,"NOR":1.592,"COL":207.644,"HAM":47.956,"BOR":218.954,"SAI":165.762,"HAD":138.814,"RUS":184.374,"PIA":2.645,"BEA":205.223}},{"lap":77,"gaps":{"VER":16.023,"LEC":0.983,"LAW":139.967,"OCO":139.25,"NOR":0.0,"HAM":47.169,"HAD":138.303,"PIA":1.859}},{"lap":78,"gaps":{"VER":20.572,"LEC":3.131,"NOR":0.0,"HAM":51.387,"PIA":3.658}}],"fastestLap":{"driver":"NOR","lap":78,"time":"1:13.221"}}